[{"id":"q-img-51b92f91080c6ff5f8","source":"智鼎题库","library":"智鼎题库","category":"图片套题","subCategory":"智鼎重点2/套题2","setName":"智鼎重点2 / 套题2","originalFile":"20.jpg","originalPath":"智鼎题库/图片真题/智鼎重点2/套题2/20.jpg","sourceRefs":[{"archive":"智鼎题库.zip","path":"智鼎题库/图片真题/智鼎重点2/套题2/20.jpg","originalFile":"20.jpg","questionNumber":"20"},{"archive":"林木互联网校招笔试题库.zip","path":"林木互联网校招笔试题库/智鼎题库/图片真题/智鼎重点2/套题2/20.jpg","originalFile":"20.jpg","questionNumber":"20"}],"questionType":"image-only","question":"智鼎重点2 / 套题2 第 20 题（整题截图）","options":[],"answer":[],"analysis":"本题为整题截图资料，截图可能包含答案标记；仅用于搜题定位、收藏、背题浏览和后续人工结构化，不进入每日计划、随机练习、模块刷题或模拟考试。","images":["assets/questions/智鼎重点2-套题2-cd1af1d1/020-cd1ddd470c.jpg"],"ocrText":"","tags":["图片题","整题截图","待OCR","智鼎重点2 / 套题2","答案外露","仅资料查看"],"importConfidence":0.45,"needsOcr":true,"answerRevealed":true,"practiceMode":"reference-only","practiceEligible":false,"answerLeakReason":"整题截图可能包含已勾选或高亮答案，不能用于先答题后看答案的普通练习。"},{"id":"q-img-615976fd3d2510d311","source":"智鼎题库","library":"智鼎题库","category":"图片套题","subCategory":"智鼎重点2/套题2","setName":"智鼎重点2 / 套题2","originalFile":"21.jpg","originalPath":"智鼎题库/图片真题/智鼎重点2/套题2/21.jpg","sourceRefs":[{"archive":"智鼎题库.zip","path":"智鼎题库/图片真题/智鼎重点2/套题2/21.jpg","originalFile":"21.jpg","questionNumber":"21"},{"archive":"林木互联网校招笔试题库.zip","path":"林木互联网校招笔试题库/智鼎题库/图片真题/智鼎重点2/套题2/21.jpg","originalFile":"21.jpg","questionNumber":"21"}],"questionType":"image-only","question":"智鼎重点2 / 套题2 第 21 题（整题截图）","options":[],"answer":[],"analysis":"本题为整题截图资料，截图可能包含答案标记；仅用于搜题定位、收藏、背题浏览和后续人工结构化，不进入每日计划、随机练习、模块刷题或模拟考试。","images":["assets/questions/智鼎重点2-套题2-cd1af1d1/021-a52e823785.jpg"],"ocrText":"","tags":["图片题","整题截图","待OCR","智鼎重点2 / 套题2","答案外露","仅资料查看"],"importConfidence":0.45,"needsOcr":true,"answerRevealed":true,"practiceMode":"reference-only","practiceEligible":false,"answerLeakReason":"整题截图可能包含已勾选或高亮答案，不能用于先答题后看答案的普通练习。"},{"id":"q-img-02d0d849aa551fe5d0","source":"智鼎题库","library":"智鼎题库","category":"图片套题","subCategory":"智鼎重点2/套题2","setName":"智鼎重点2 / 套题2","originalFile":"22.jpg","originalPath":"智鼎题库/图片真题/智鼎重点2/套题2/22.jpg","sourceRefs":[{"archive":"智鼎题库.zip","path":"智鼎题库/图片真题/智鼎重点2/套题2/22.jpg","originalFile":"22.jpg","questionNumber":"22"},{"archive":"林木互联网校招笔试题库.zip","path":"林木互联网校招笔试题库/智鼎题库/图片真题/智鼎重点2/套题2/22.jpg","originalFile":"22.jpg","questionNumber":"22"}],"questionType":"image-only","question":"智鼎重点2 / 套题2 第 22 题（整题截图）","options":[],"answer":[],"analysis":"本题为整题截图资料，截图可能包含答案标记；仅用于搜题定位、收藏、背题浏览和后续人工结构化，不进入每日计划、随机练习、模块刷题或模拟考试。","images":["assets/questions/智鼎重点2-套题2-cd1af1d1/022-ec017e7e98.jpg"],"ocrText":"","tags":["图片题","整题截图","待OCR","智鼎重点2 / 套题2","答案外露","仅资料查看"],"importConfidence":0.45,"needsOcr":true,"answerRevealed":true,"practiceMode":"reference-only","practiceEligible":false,"answerLeakReason":"整题截图可能包含已勾选或高亮答案，不能用于先答题后看答案的普通练习。"},{"id":"q-img-a5d2a3173fde7216a8","source":"智鼎题库","library":"智鼎题库","category":"图片套题","subCategory":"智鼎重点2/套题2","setName":"智鼎重点2 / 套题2","originalFile":"23.jpg","originalPath":"智鼎题库/图片真题/智鼎重点2/套题2/23.jpg","sourceRefs":[{"archive":"智鼎题库.zip","path":"智鼎题库/图片真题/智鼎重点2/套题2/23.jpg","originalFile":"23.jpg","questionNumber":"23"},{"archive":"林木互联网校招笔试题库.zip","path":"林木互联网校招笔试题库/智鼎题库/图片真题/智鼎重点2/套题2/23.jpg","originalFile":"23.jpg","questionNumber":"23"}],"questionType":"image-only","question":"智鼎重点2 / 套题2 第 23 题（整题截图）","options":[],"answer":[],"analysis":"本题为整题截图资料，截图可能包含答案标记；仅用于搜题定位、收藏、背题浏览和后续人工结构化，不进入每日计划、随机练习、模块刷题或模拟考试。","images":["assets/questions/智鼎重点2-套题2-cd1af1d1/023-9e6a6de07f.jpg"],"ocrText":"","tags":["图片题","整题截图","待OCR","智鼎重点2 / 套题2","答案外露","仅资料查看"],"importConfidence":0.45,"needsOcr":true,"answerRevealed":true,"practiceMode":"reference-only","practiceEligible":false,"answerLeakReason":"整题截图可能包含已勾选或高亮答案，不能用于先答题后看答案的普通练习。"},{"id":"q-img-7521c145e008455b1c","source":"智鼎题库","library":"智鼎题库","category":"图片套题","subCategory":"智鼎重点2/套题2","setName":"智鼎重点2 / 套题2","originalFile":"24.jpg","originalPath":"智鼎题库/图片真题/智鼎重点2/套题2/24.jpg","sourceRefs":[{"archive":"智鼎题库.zip","path":"智鼎题库/图片真题/智鼎重点2/套题2/24.jpg","originalFile":"24.jpg","questionNumber":"24"},{"archive":"林木互联网校招笔试题库.zip","path":"林木互联网校招笔试题库/智鼎题库/图片真题/智鼎重点2/套题2/24.jpg","originalFile":"24.jpg","questionNumber":"24"}],"questionType":"image-only","question":"智鼎重点2 / 套题2 第 24 题（整题截图）","options":[],"answer":[],"analysis":"本题为整题截图资料，截图可能包含答案标记；仅用于搜题定位、收藏、背题浏览和后续人工结构化，不进入每日计划、随机练习、模块刷题或模拟考试。","images":["assets/questions/智鼎重点2-套题2-cd1af1d1/024-e38c8be449.jpg"],"ocrText":"","tags":["图片题","整题截图","待OCR","智鼎重点2 / 套题2","答案外露","仅资料查看"],"importConfidence":0.45,"needsOcr":true,"answerRevealed":true,"practiceMode":"reference-only","practiceEligible":false,"answerLeakReason":"整题截图可能包含已勾选或高亮答案，不能用于先答题后看答案的普通练习。"},{"id":"q-img-4e3597519528689b10","source":"智鼎题库","library":"智鼎题库","category":"图片套题","subCategory":"智鼎重点2/套题2","setName":"智鼎重点2 / 套题2","originalFile":"25.jpg","originalPath":"智鼎题库/图片真题/智鼎重点2/套题2/25.jpg","sourceRefs":[{"archive":"智鼎题库.zip","path":"智鼎题库/图片真题/智鼎重点2/套题2/25.jpg","originalFile":"25.jpg","questionNumber":"25"},{"archive":"林木互联网校招笔试题库.zip","path":"林木互联网校招笔试题库/智鼎题库/图片真题/智鼎重点2/套题2/25.jpg","originalFile":"25.jpg","questionNumber":"25"}],"questionType":"image-only","question":"智鼎重点2 / 套题2 第 25 题（整题截图）","options":[],"answer":[],"analysis":"本题为整题截图资料，截图可能包含答案标记；仅用于搜题定位、收藏、背题浏览和后续人工结构化，不进入每日计划、随机练习、模块刷题或模拟考试。","images":["assets/questions/智鼎重点2-套题2-cd1af1d1/025-debd4ddd65.jpg"],"ocrText":"","tags":["图片题","整题截图","待OCR","智鼎重点2 / 套题2","答案外露","仅资料查看"],"importConfidence":0.45,"needsOcr":true,"answerRevealed":true,"practiceMode":"reference-only","practiceEligible":false,"answerLeakReason":"整题截图可能包含已勾选或高亮答案，不能用于先答题后看答案的普通练习。"},{"id":"q-img-6992d7f7a8facc6098","source":"智鼎题库","library":"智鼎题库","category":"图片套题","subCategory":"智鼎重点2/套题2","setName":"智鼎重点2 / 套题2","originalFile":"26.jpg","originalPath":"智鼎题库/图片真题/智鼎重点2/套题2/26.jpg","sourceRefs":[{"archive":"智鼎题库.zip","path":"智鼎题库/图片真题/智鼎重点2/套题2/26.jpg","originalFile":"26.jpg","questionNumber":"26"},{"archive":"林木互联网校招笔试题库.zip","path":"林木互联网校招笔试题库/智鼎题库/图片真题/智鼎重点2/套题2/26.jpg","originalFile":"26.jpg","questionNumber":"26"}],"questionType":"image-only","question":"智鼎重点2 / 套题2 第 26 题（整题截图）","options":[],"answer":[],"analysis":"本题为整题截图资料，截图可能包含答案标记；仅用于搜题定位、收藏、背题浏览和后续人工结构化，不进入每日计划、随机练习、模块刷题或模拟考试。","images":["assets/questions/智鼎重点2-套题2-cd1af1d1/026-7c62f57620.jpg"],"ocrText":"","tags":["图片题","整题截图","待OCR","智鼎重点2 / 套题2","答案外露","仅资料查看"],"importConfidence":0.45,"needsOcr":true,"answerRevealed":true,"practiceMode":"reference-only","practiceEligible":false,"answerLeakReason":"整题截图可能包含已勾选或高亮答案，不能用于先答题后看答案的普通练习。"},{"id":"q-img-b7df08102e2d508630","source":"智鼎题库","library":"智鼎题库","category":"图片套题","subCategory":"智鼎重点2/套题2","setName":"智鼎重点2 / 套题2","originalFile":"27.png","originalPath":"智鼎题库/图片真题/智鼎重点2/套题2/27.png","sourceRefs":[{"archive":"智鼎题库.zip","path":"智鼎题库/图片真题/智鼎重点2/套题2/27.png","originalFile":"27.png","questionNumber":"27"},{"archive":"林木互联网校招笔试题库.zip","path":"林木互联网校招笔试题库/智鼎题库/图片真题/智鼎重点2/套题2/27.png","originalFile":"27.png","questionNumber":"27"}],"questionType":"image-only","question":"智鼎重点2 / 套题2 第 27 题（整题截图）","options":[],"answer":[],"analysis":"本题为整题截图资料，截图可能包含答案标记；仅用于搜题定位、收藏、背题浏览和后续人工结构化，不进入每日计划、随机练习、模块刷题或模拟考试。","images":["assets/questions/智鼎重点2-套题2-cd1af1d1/027-97b1cea65b.png"],"ocrText":"","tags":["图片题","整题截图","待OCR","智鼎重点2 / 套题2","答案外露","仅资料查看"],"importConfidence":0.45,"needsOcr":true,"answerRevealed":true,"practiceMode":"reference-only","practiceEligible":false,"answerLeakReason":"整题截图可能包含已勾选或高亮答案，不能用于先答题后看答案的普通练习。"},{"id":"q-img-c74c9aa08788b74c80","source":"智鼎题库","library":"智鼎题库","category":"图片套题","subCategory":"智鼎重点2/套题2","setName":"智鼎重点2 / 套题2","originalFile":"28.png","originalPath":"智鼎题库/图片真题/智鼎重点2/套题2/28.png","sourceRefs":[{"archive":"智鼎题库.zip","path":"智鼎题库/图片真题/智鼎重点2/套题2/28.png","originalFile":"28.png","questionNumber":"28"},{"archive":"林木互联网校招笔试题库.zip","path":"林木互联网校招笔试题库/智鼎题库/图片真题/智鼎重点2/套题2/28.png","originalFile":"28.png","questionNumber":"28"}],"questionType":"image-only","question":"智鼎重点2 / 套题2 第 28 题（整题截图）","options":[],"answer":[],"analysis":"本题为整题截图资料，截图可能包含答案标记；仅用于搜题定位、收藏、背题浏览和后续人工结构化，不进入每日计划、随机练习、模块刷题或模拟考试。","images":["assets/questions/智鼎重点2-套题2-cd1af1d1/028-04149bd54e.png"],"ocrText":"","tags":["图片题","整题截图","待OCR","智鼎重点2 / 套题2","答案外露","仅资料查看"],"importConfidence":0.45,"needsOcr":true,"answerRevealed":true,"practiceMode":"reference-only","practiceEligible":false,"answerLeakReason":"整题截图可能包含已勾选或高亮答案，不能用于先答题后看答案的普通练习。"},{"id":"q-img-baa3675a17033eb476","source":"智鼎题库","library":"智鼎题库","category":"图片套题","subCategory":"智鼎重点2/套题2","setName":"智鼎重点2 / 套题2","originalFile":"29.png","originalPath":"智鼎题库/图片真题/智鼎重点2/套题2/29.png","sourceRefs":[{"archive":"智鼎题库.zip","path":"智鼎题库/图片真题/智鼎重点2/套题2/29.png","originalFile":"29.png","questionNumber":"29"},{"archive":"林木互联网校招笔试题库.zip","path":"林木互联网校招笔试题库/智鼎题库/图片真题/智鼎重点2/套题2/29.png","originalFile":"29.png","questionNumber":"29"}],"questionType":"image-only","question":"智鼎重点2 / 套题2 第 29 题（整题截图）","options":[],"answer":[],"analysis":"本题为整题截图资料，截图可能包含答案标记；仅用于搜题定位、收藏、背题浏览和后续人工结构化，不进入每日计划、随机练习、模块刷题或模拟考试。","images":["assets/questions/智鼎重点2-套题2-cd1af1d1/029-4e0ffa1680.png"],"ocrText":"","tags":["图片题","整题截图","待OCR","智鼎重点2 / 套题2","答案外露","仅资料查看"],"importConfidence":0.45,"needsOcr":true,"answerRevealed":true,"practiceMode":"reference-only","practiceEligible":false,"answerLeakReason":"整题截图可能包含已勾选或高亮答案，不能用于先答题后看答案的普通练习。"},{"id":"q-img-95fdb9026d4c283d5b","source":"智鼎题库","library":"智鼎题库","category":"图片套题","subCategory":"智鼎重点2/套题2","setName":"智鼎重点2 / 套题2","originalFile":"30.png","originalPath":"智鼎题库/图片真题/智鼎重点2/套题2/30.png","sourceRefs":[{"archive":"智鼎题库.zip","path":"智鼎题库/图片真题/智鼎重点2/套题2/30.png","originalFile":"30.png","questionNumber":"30"},{"archive":"林木互联网校招笔试题库.zip","path":"林木互联网校招笔试题库/智鼎题库/图片真题/智鼎重点2/套题2/30.png","originalFile":"30.png","questionNumber":"30"}],"questionType":"image-only","question":"智鼎重点2 / 套题2 第 30 题（整题截图）","options":[],"answer":[],"analysis":"本题为整题截图资料，截图可能包含答案标记；仅用于搜题定位、收藏、背题浏览和后续人工结构化，不进入每日计划、随机练习、模块刷题或模拟考试。","images":["assets/questions/智鼎重点2-套题2-cd1af1d1/030-96a3e54055.png"],"ocrText":"","tags":["图片题","整题截图","待OCR","智鼎重点2 / 套题2","答案外露","仅资料查看"],"importConfidence":0.45,"needsOcr":true,"answerRevealed":true,"practiceMode":"reference-only","practiceEligible":false,"answerLeakReason":"整题截图可能包含已勾选或高亮答案，不能用于先答题后看答案的普通练习。"},{"id":"q-img-15ab8d8fc0d7195738","source":"智鼎题库","library":"智鼎题库","category":"图片套题","subCategory":"智鼎重点2/套题2","setName":"智鼎重点2 / 套题2","originalFile":"31.png","originalPath":"智鼎题库/图片真题/智鼎重点2/套题2/31.png","sourceRefs":[{"archive":"智鼎题库.zip","path":"智鼎题库/图片真题/智鼎重点2/套题2/31.png","originalFile":"31.png","questionNumber":"31"},{"archive":"林木互联网校招笔试题库.zip","path":"林木互联网校招笔试题库/智鼎题库/图片真题/智鼎重点2/套题2/31.png","originalFile":"31.png","questionNumber":"31"}],"questionType":"image-only","question":"智鼎重点2 / 套题2 第 31 题（整题截图）","options":[],"answer":[],"analysis":"本题为整题截图资料，截图可能包含答案标记；仅用于搜题定位、收藏、背题浏览和后续人工结构化，不进入每日计划、随机练习、模块刷题或模拟考试。","images":["assets/questions/智鼎重点2-套题2-cd1af1d1/031-8478559e1e.png"],"ocrText":"","tags":["图片题","整题截图","待OCR","智鼎重点2 / 套题2","答案外露","仅资料查看"],"importConfidence":0.45,"needsOcr":true,"answerRevealed":true,"practiceMode":"reference-only","practiceEligible":false,"answerLeakReason":"整题截图可能包含已勾选或高亮答案，不能用于先答题后看答案的普通练习。"},{"id":"q-img-6f9a8aefab7c4890ec","source":"智鼎题库","library":"智鼎题库","category":"图片套题","subCategory":"智鼎重点2/套题2","setName":"智鼎重点2 / 套题2","originalFile":"32.png","originalPath":"智鼎题库/图片真题/智鼎重点2/套题2/32.png","sourceRefs":[{"archive":"智鼎题库.zip","path":"智鼎题库/图片真题/智鼎重点2/套题2/32.png","originalFile":"32.png","questionNumber":"32"},{"archive":"林木互联网校招笔试题库.zip","path":"林木互联网校招笔试题库/智鼎题库/图片真题/智鼎重点2/套题2/32.png","originalFile":"32.png","questionNumber":"32"}],"questionType":"image-only","question":"智鼎重点2 / 套题2 第 32 题（整题截图）","options":[],"answer":[],"analysis":"本题为整题截图资料，截图可能包含答案标记；仅用于搜题定位、收藏、背题浏览和后续人工结构化，不进入每日计划、随机练习、模块刷题或模拟考试。","images":["assets/questions/智鼎重点2-套题2-cd1af1d1/032-4ef941aa8c.png"],"ocrText":"","tags":["图片题","整题截图","待OCR","智鼎重点2 / 套题2","答案外露","仅资料查看"],"importConfidence":0.45,"needsOcr":true,"answerRevealed":true,"practiceMode":"reference-only","practiceEligible":false,"answerLeakReason":"整题截图可能包含已勾选或高亮答案，不能用于先答题后看答案的普通练习。"},{"id":"q-img-747fe1794b17010c3c","source":"智鼎题库","library":"智鼎题库","category":"图片套题","subCategory":"智鼎重点2/套题2","setName":"智鼎重点2 / 套题2","originalFile":"33.png","originalPath":"智鼎题库/图片真题/智鼎重点2/套题2/33.png","sourceRefs":[{"archive":"智鼎题库.zip","path":"智鼎题库/图片真题/智鼎重点2/套题2/33.png","originalFile":"33.png","questionNumber":"33"},{"archive":"林木互联网校招笔试题库.zip","path":"林木互联网校招笔试题库/智鼎题库/图片真题/智鼎重点2/套题2/33.png","originalFile":"33.png","questionNumber":"33"}],"questionType":"image-only","question":"智鼎重点2 / 套题2 第 33 题（整题截图）","options":[],"answer":[],"analysis":"本题为整题截图资料，截图可能包含答案标记；仅用于搜题定位、收藏、背题浏览和后续人工结构化，不进入每日计划、随机练习、模块刷题或模拟考试。","images":["assets/questions/智鼎重点2-套题2-cd1af1d1/033-b7e4aeebfa.png"],"ocrText":"","tags":["图片题","整题截图","待OCR","智鼎重点2 / 套题2","答案外露","仅资料查看"],"importConfidence":0.45,"needsOcr":true,"answerRevealed":true,"practiceMode":"reference-only","practiceEligible":false,"answerLeakReason":"整题截图可能包含已勾选或高亮答案，不能用于先答题后看答案的普通练习。"},{"id":"q-img-42eb1ef5a28972a37b","source":"智鼎题库","library":"智鼎题库","category":"图片套题","subCategory":"智鼎重点2/套题2","setName":"智鼎重点2 / 套题2","originalFile":"34.png","originalPath":"智鼎题库/图片真题/智鼎重点2/套题2/34.png","sourceRefs":[{"archive":"智鼎题库.zip","path":"智鼎题库/图片真题/智鼎重点2/套题2/34.png","originalFile":"34.png","questionNumber":"34"},{"archive":"林木互联网校招笔试题库.zip","path":"林木互联网校招笔试题库/智鼎题库/图片真题/智鼎重点2/套题2/34.png","originalFile":"34.png","questionNumber":"34"}],"questionType":"image-only","question":"智鼎重点2 / 套题2 第 34 题（整题截图）","options":[],"answer":[],"analysis":"本题为整题截图资料，截图可能包含答案标记；仅用于搜题定位、收藏、背题浏览和后续人工结构化，不进入每日计划、随机练习、模块刷题或模拟考试。","images":["assets/questions/智鼎重点2-套题2-cd1af1d1/034-1837464415.png"],"ocrText":"","tags":["图片题","整题截图","待OCR","智鼎重点2 / 套题2","答案外露","仅资料查看"],"importConfidence":0.45,"needsOcr":true,"answerRevealed":true,"practiceMode":"reference-only","practiceEligible":false,"answerLeakReason":"整题截图可能包含已勾选或高亮答案，不能用于先答题后看答案的普通练习。"},{"id":"q-img-ec25e92c5c98c5bf54","source":"智鼎题库","library":"智鼎题库","category":"图片套题","subCategory":"智鼎重点2/套题2","setName":"智鼎重点2 / 套题2","originalFile":"35.png","originalPath":"智鼎题库/图片真题/智鼎重点2/套题2/35.png","sourceRefs":[{"archive":"智鼎题库.zip","path":"智鼎题库/图片真题/智鼎重点2/套题2/35.png","originalFile":"35.png","questionNumber":"35"},{"archive":"林木互联网校招笔试题库.zip","path":"林木互联网校招笔试题库/智鼎题库/图片真题/智鼎重点2/套题2/35.png","originalFile":"35.png","questionNumber":"35"}],"questionType":"image-only","question":"智鼎重点2 / 套题2 第 35 题（整题截图）","options":[],"answer":[],"analysis":"本题为整题截图资料，截图可能包含答案标记；仅用于搜题定位、收藏、背题浏览和后续人工结构化，不进入每日计划、随机练习、模块刷题或模拟考试。","images":["assets/questions/智鼎重点2-套题2-cd1af1d1/035-0f9ae59295.png"],"ocrText":"","tags":["图片题","整题截图","待OCR","智鼎重点2 / 套题2","答案外露","仅资料查看"],"importConfidence":0.45,"needsOcr":true,"answerRevealed":true,"practiceMode":"reference-only","practiceEligible":false,"answerLeakReason":"整题截图可能包含已勾选或高亮答案，不能用于先答题后看答案的普通练习。"},{"id":"q-img-e980925a442ed6e34b","source":"智鼎题库","library":"智鼎题库","category":"图片套题","subCategory":"智鼎重点2/套题2","setName":"智鼎重点2 / 套题2","originalFile":"36.png","originalPath":"智鼎题库/图片真题/智鼎重点2/套题2/36.png","sourceRefs":[{"archive":"智鼎题库.zip","path":"智鼎题库/图片真题/智鼎重点2/套题2/36.png","originalFile":"36.png","questionNumber":"36"},{"archive":"林木互联网校招笔试题库.zip","path":"林木互联网校招笔试题库/智鼎题库/图片真题/智鼎重点2/套题2/36.png","originalFile":"36.png","questionNumber":"36"}],"questionType":"image-only","question":"智鼎重点2 / 套题2 第 36 题（整题截图）","options":[],"answer":[],"analysis":"本题为整题截图资料，截图可能包含答案标记；仅用于搜题定位、收藏、背题浏览和后续人工结构化，不进入每日计划、随机练习、模块刷题或模拟考试。","images":["assets/questions/智鼎重点2-套题2-cd1af1d1/036-336cdad7c0.png"],"ocrText":"","tags":["图片题","整题截图","待OCR","智鼎重点2 / 套题2","答案外露","仅资料查看"],"importConfidence":0.45,"needsOcr":true,"answerRevealed":true,"practiceMode":"reference-only","practiceEligible":false,"answerLeakReason":"整题截图可能包含已勾选或高亮答案，不能用于先答题后看答案的普通练习。"},{"id":"q-img-bf8a43b2f3332a1108","source":"智鼎题库","library":"智鼎题库","category":"图片套题","subCategory":"智鼎重点2/套题2","setName":"智鼎重点2 / 套题2","originalFile":"37.jpg","originalPath":"智鼎题库/图片真题/智鼎重点2/套题2/37.jpg","sourceRefs":[{"archive":"智鼎题库.zip","path":"智鼎题库/图片真题/智鼎重点2/套题2/37.jpg","originalFile":"37.jpg","questionNumber":"37"},{"archive":"林木互联网校招笔试题库.zip","path":"林木互联网校招笔试题库/智鼎题库/图片真题/智鼎重点2/套题2/37.jpg","originalFile":"37.jpg","questionNumber":"37"}],"questionType":"image-only","question":"智鼎重点2 / 套题2 第 37 题（整题截图）","options":[],"answer":[],"analysis":"本题为整题截图资料，截图可能包含答案标记；仅用于搜题定位、收藏、背题浏览和后续人工结构化，不进入每日计划、随机练习、模块刷题或模拟考试。","images":["assets/questions/智鼎重点2-套题2-cd1af1d1/037-1fd590c99c.jpg"],"ocrText":"","tags":["图片题","整题截图","待OCR","智鼎重点2 / 套题2","答案外露","仅资料查看"],"importConfidence":0.45,"needsOcr":true,"answerRevealed":true,"practiceMode":"reference-only","practiceEligible":false,"answerLeakReason":"整题截图可能包含已勾选或高亮答案，不能用于先答题后看答案的普通练习。"},{"id":"q-img-6f1f742651cd1cdd6a","source":"智鼎题库","library":"智鼎题库","category":"图片套题","subCategory":"智鼎重点2/套题2","setName":"智鼎重点2 / 套题2","originalFile":"38.png","originalPath":"智鼎题库/图片真题/智鼎重点2/套题2/38.png","sourceRefs":[{"archive":"智鼎题库.zip","path":"智鼎题库/图片真题/智鼎重点2/套题2/38.png","originalFile":"38.png","questionNumber":"38"},{"archive":"林木互联网校招笔试题库.zip","path":"林木互联网校招笔试题库/智鼎题库/图片真题/智鼎重点2/套题2/38.png","originalFile":"38.png","questionNumber":"38"}],"questionType":"image-only","question":"智鼎重点2 / 套题2 第 38 题（整题截图）","options":[],"answer":[],"analysis":"本题为整题截图资料，截图可能包含答案标记；仅用于搜题定位、收藏、背题浏览和后续人工结构化，不进入每日计划、随机练习、模块刷题或模拟考试。","images":["assets/questions/智鼎重点2-套题2-cd1af1d1/038-df5697e751.png"],"ocrText":"","tags":["图片题","整题截图","待OCR","智鼎重点2 / 套题2","答案外露","仅资料查看"],"importConfidence":0.45,"needsOcr":true,"answerRevealed":true,"practiceMode":"reference-only","practiceEligible":false,"answerLeakReason":"整题截图可能包含已勾选或高亮答案，不能用于先答题后看答案的普通练习。"},{"id":"q-img-c482eee3105c42db86","source":"智鼎题库","library":"智鼎题库","category":"图片套题","subCategory":"智鼎重点2/套题2","setName":"智鼎重点2 / 套题2","originalFile":"39.jpg","originalPath":"智鼎题库/图片真题/智鼎重点2/套题2/39.jpg","sourceRefs":[{"archive":"智鼎题库.zip","path":"智鼎题库/图片真题/智鼎重点2/套题2/39.jpg","originalFile":"39.jpg","questionNumber":"39"},{"archive":"林木互联网校招笔试题库.zip","path":"林木互联网校招笔试题库/智鼎题库/图片真题/智鼎重点2/套题2/39.jpg","originalFile":"39.jpg","questionNumber":"39"}],"questionType":"image-only","question":"智鼎重点2 / 套题2 第 39 题（整题截图）","options":[],"answer":[],"analysis":"本题为整题截图资料，截图可能包含答案标记；仅用于搜题定位、收藏、背题浏览和后续人工结构化，不进入每日计划、随机练习、模块刷题或模拟考试。","images":["assets/questions/智鼎重点2-套题2-cd1af1d1/039-339e761bdd.jpg"],"ocrText":"","tags":["图片题","整题截图","待OCR","智鼎重点2 / 套题2","答案外露","仅资料查看"],"importConfidence":0.45,"needsOcr":true,"answerRevealed":true,"practiceMode":"reference-only","practiceEligible":false,"answerLeakReason":"整题截图可能包含已勾选或高亮答案，不能用于先答题后看答案的普通练习。"},{"id":"q-img-85b764381f3f32203f","source":"智鼎题库","library":"智鼎题库","category":"图片套题","subCategory":"智鼎重点2/套题2","setName":"智鼎重点2 / 套题2","originalFile":"40.jpg","originalPath":"智鼎题库/图片真题/智鼎重点2/套题2/40.jpg","sourceRefs":[{"archive":"智鼎题库.zip","path":"智鼎题库/图片真题/智鼎重点2/套题2/40.jpg","originalFile":"40.jpg","questionNumber":"40"},{"archive":"林木互联网校招笔试题库.zip","path":"林木互联网校招笔试题库/智鼎题库/图片真题/智鼎重点2/套题2/40.jpg","originalFile":"40.jpg","questionNumber":"40"}],"questionType":"image-only","question":"智鼎重点2 / 套题2 第 40 题（整题截图）","options":[],"answer":[],"analysis":"本题为整题截图资料，截图可能包含答案标记；仅用于搜题定位、收藏、背题浏览和后续人工结构化，不进入每日计划、随机练习、模块刷题或模拟考试。","images":["assets/questions/智鼎重点2-套题2-cd1af1d1/040-152b8ff4a7.jpg"],"ocrText":"","tags":["图片题","整题截图","待OCR","智鼎重点2 / 套题2","答案外露","仅资料查看"],"importConfidence":0.45,"needsOcr":true,"answerRevealed":true,"practiceMode":"reference-only","practiceEligible":false,"answerLeakReason":"整题截图可能包含已勾选或高亮答案，不能用于先答题后看答案的普通练习。"},{"id":"q-img-c4e7ceb28bd0b1bf99","source":"智鼎题库","library":"智鼎题库","category":"图片套题","subCategory":"智鼎重点2/套题2","setName":"智鼎重点2 / 套题2","originalFile":"41.jpg","originalPath":"智鼎题库/图片真题/智鼎重点2/套题2/41.jpg","sourceRefs":[{"archive":"智鼎题库.zip","path":"智鼎题库/图片真题/智鼎重点2/套题2/41.jpg","originalFile":"41.jpg","questionNumber":"41"},{"archive":"林木互联网校招笔试题库.zip","path":"林木互联网校招笔试题库/智鼎题库/图片真题/智鼎重点2/套题2/41.jpg","originalFile":"41.jpg","questionNumber":"41"}],"questionType":"image-only","question":"智鼎重点2 / 套题2 第 41 题（整题截图）","options":[],"answer":[],"analysis":"本题为整题截图资料，截图可能包含答案标记；仅用于搜题定位、收藏、背题浏览和后续人工结构化，不进入每日计划、随机练习、模块刷题或模拟考试。","images":["assets/questions/智鼎重点2-套题2-cd1af1d1/041-42f1cd3791.jpg"],"ocrText":"","tags":["图片题","整题截图","待OCR","智鼎重点2 / 套题2","答案外露","仅资料查看"],"importConfidence":0.45,"needsOcr":true,"answerRevealed":true,"practiceMode":"reference-only","practiceEligible":false,"answerLeakReason":"整题截图可能包含已勾选或高亮答案，不能用于先答题后看答案的普通练习。"},{"id":"q-img-beba07027ad3dbb4f5","source":"智鼎题库","library":"智鼎题库","category":"图片套题","subCategory":"智鼎重点2/套题2","setName":"智鼎重点2 / 套题2","originalFile":"42.jpg","originalPath":"智鼎题库/图片真题/智鼎重点2/套题2/42.jpg","sourceRefs":[{"archive":"智鼎题库.zip","path":"智鼎题库/图片真题/智鼎重点2/套题2/42.jpg","originalFile":"42.jpg","questionNumber":"42"},{"archive":"林木互联网校招笔试题库.zip","path":"林木互联网校招笔试题库/智鼎题库/图片真题/智鼎重点2/套题2/42.jpg","originalFile":"42.jpg","questionNumber":"42"}],"questionType":"image-only","question":"智鼎重点2 / 套题2 第 42 题（整题截图）","options":[],"answer":[],"analysis":"本题为整题截图资料，截图可能包含答案标记；仅用于搜题定位、收藏、背题浏览和后续人工结构化，不进入每日计划、随机练习、模块刷题或模拟考试。","images":["assets/questions/智鼎重点2-套题2-cd1af1d1/042-8f5ddea026.jpg"],"ocrText":"","tags":["图片题","整题截图","待OCR","智鼎重点2 / 套题2","答案外露","仅资料查看"],"importConfidence":0.45,"needsOcr":true,"answerRevealed":true,"practiceMode":"reference-only","practiceEligible":false,"answerLeakReason":"整题截图可能包含已勾选或高亮答案，不能用于先答题后看答案的普通练习。"},{"id":"q-img-0a4fc1cb9a124ac757","source":"智鼎题库","library":"智鼎题库","category":"图片套题","subCategory":"智鼎重点2/套题2","setName":"智鼎重点2 / 套题2","originalFile":"43.png","originalPath":"智鼎题库/图片真题/智鼎重点2/套题2/43.png","sourceRefs":[{"archive":"智鼎题库.zip","path":"智鼎题库/图片真题/智鼎重点2/套题2/43.png","originalFile":"43.png","questionNumber":"43"},{"archive":"林木互联网校招笔试题库.zip","path":"林木互联网校招笔试题库/智鼎题库/图片真题/智鼎重点2/套题2/43.png","originalFile":"43.png","questionNumber":"43"}],"questionType":"image-only","question":"智鼎重点2 / 套题2 第 43 题（整题截图）","options":[],"answer":[],"analysis":"本题为整题截图资料，截图可能包含答案标记；仅用于搜题定位、收藏、背题浏览和后续人工结构化，不进入每日计划、随机练习、模块刷题或模拟考试。","images":["assets/questions/智鼎重点2-套题2-cd1af1d1/043-62f89e8413.png"],"ocrText":"","tags":["图片题","整题截图","待OCR","智鼎重点2 / 套题2","答案外露","仅资料查看"],"importConfidence":0.45,"needsOcr":true,"answerRevealed":true,"practiceMode":"reference-only","practiceEligible":false,"answerLeakReason":"整题截图可能包含已勾选或高亮答案，不能用于先答题后看答案的普通练习。"},{"id":"q-img-fc78b203a6024b6726","source":"智鼎题库","library":"智鼎题库","category":"图片套题","subCategory":"智鼎重点2/套题2","setName":"智鼎重点2 / 套题2","originalFile":"44.jpg","originalPath":"智鼎题库/图片真题/智鼎重点2/套题2/44.jpg","sourceRefs":[{"archive":"智鼎题库.zip","path":"智鼎题库/图片真题/智鼎重点2/套题2/44.jpg","originalFile":"44.jpg","questionNumber":"44"},{"archive":"林木互联网校招笔试题库.zip","path":"林木互联网校招笔试题库/智鼎题库/图片真题/智鼎重点2/套题2/44.jpg","originalFile":"44.jpg","questionNumber":"44"}],"questionType":"image-only","question":"智鼎重点2 / 套题2 第 44 题（整题截图）","options":[],"answer":[],"analysis":"本题为整题截图资料，截图可能包含答案标记；仅用于搜题定位、收藏、背题浏览和后续人工结构化，不进入每日计划、随机练习、模块刷题或模拟考试。","images":["assets/questions/智鼎重点2-套题2-cd1af1d1/044-42269d97ed.jpg"],"ocrText":"","tags":["图片题","整题截图","待OCR","智鼎重点2 / 套题2","答案外露","仅资料查看"],"importConfidence":0.45,"needsOcr":true,"answerRevealed":true,"practiceMode":"reference-only","practiceEligible":false,"answerLeakReason":"整题截图可能包含已勾选或高亮答案，不能用于先答题后看答案的普通练习。"},{"id":"q-img-24e630a4bf28eb3fc9","source":"智鼎题库","library":"智鼎题库","category":"图片套题","subCategory":"智鼎重点2/套题2","setName":"智鼎重点2 / 套题2","originalFile":"45.jpg","originalPath":"智鼎题库/图片真题/智鼎重点2/套题2/45.jpg","sourceRefs":[{"archive":"智鼎题库.zip","path":"智鼎题库/图片真题/智鼎重点2/套题2/45.jpg","originalFile":"45.jpg","questionNumber":"45"},{"archive":"林木互联网校招笔试题库.zip","path":"林木互联网校招笔试题库/智鼎题库/图片真题/智鼎重点2/套题2/45.jpg","originalFile":"45.jpg","questionNumber":"45"}],"questionType":"image-only","question":"智鼎重点2 / 套题2 第 45 题（整题截图）","options":[],"answer":[],"analysis":"本题为整题截图资料，截图可能包含答案标记；仅用于搜题定位、收藏、背题浏览和后续人工结构化，不进入每日计划、随机练习、模块刷题或模拟考试。","images":["assets/questions/智鼎重点2-套题2-cd1af1d1/045-758cc9827c.jpg"],"ocrText":"","tags":["图片题","整题截图","待OCR","智鼎重点2 / 套题2","答案外露","仅资料查看"],"importConfidence":0.45,"needsOcr":true,"answerRevealed":true,"practiceMode":"reference-only","practiceEligible":false,"answerLeakReason":"整题截图可能包含已勾选或高亮答案，不能用于先答题后看答案的普通练习。"},{"id":"q-img-d8060bfd3a951433d8","source":"智鼎题库","library":"智鼎题库","category":"图片套题","subCategory":"智鼎重点2/套题2","setName":"智鼎重点2 / 套题2","originalFile":"46.jpg","originalPath":"智鼎题库/图片真题/智鼎重点2/套题2/46.jpg","sourceRefs":[{"archive":"智鼎题库.zip","path":"智鼎题库/图片真题/智鼎重点2/套题2/46.jpg","originalFile":"46.jpg","questionNumber":"46"},{"archive":"林木互联网校招笔试题库.zip","path":"林木互联网校招笔试题库/智鼎题库/图片真题/智鼎重点2/套题2/46.jpg","originalFile":"46.jpg","questionNumber":"46"}],"questionType":"image-only","question":"智鼎重点2 / 套题2 第 46 题（整题截图）","options":[],"answer":[],"analysis":"本题为整题截图资料，截图可能包含答案标记；仅用于搜题定位、收藏、背题浏览和后续人工结构化，不进入每日计划、随机练习、模块刷题或模拟考试。","images":["assets/questions/智鼎重点2-套题2-cd1af1d1/046-76c08093de.jpg"],"ocrText":"","tags":["图片题","整题截图","待OCR","智鼎重点2 / 套题2","答案外露","仅资料查看"],"importConfidence":0.45,"needsOcr":true,"answerRevealed":true,"practiceMode":"reference-only","practiceEligible":false,"answerLeakReason":"整题截图可能包含已勾选或高亮答案，不能用于先答题后看答案的普通练习。"},{"id":"q-img-81a830f693b026041f","source":"智鼎题库","library":"智鼎题库","category":"图片套题","subCategory":"智鼎重点2/套题2","setName":"智鼎重点2 / 套题2","originalFile":"47.jpg","originalPath":"智鼎题库/图片真题/智鼎重点2/套题2/47.jpg","sourceRefs":[{"archive":"智鼎题库.zip","path":"智鼎题库/图片真题/智鼎重点2/套题2/47.jpg","originalFile":"47.jpg","questionNumber":"47"},{"archive":"林木互联网校招笔试题库.zip","path":"林木互联网校招笔试题库/智鼎题库/图片真题/智鼎重点2/套题2/47.jpg","originalFile":"47.jpg","questionNumber":"47"}],"questionType":"image-only","question":"智鼎重点2 / 套题2 第 47 题（整题截图）","options":[],"answer":[],"analysis":"本题为整题截图资料，截图可能包含答案标记；仅用于搜题定位、收藏、背题浏览和后续人工结构化，不进入每日计划、随机练习、模块刷题或模拟考试。","images":["assets/questions/智鼎重点2-套题2-cd1af1d1/047-dc7b778d4e.jpg"],"ocrText":"","tags":["图片题","整题截图","待OCR","智鼎重点2 / 套题2","答案外露","仅资料查看"],"importConfidence":0.45,"needsOcr":true,"answerRevealed":true,"practiceMode":"reference-only","practiceEligible":false,"answerLeakReason":"整题截图可能包含已勾选或高亮答案，不能用于先答题后看答案的普通练习。"},{"id":"q-img-5b44ee96564dd64b7f","source":"智鼎题库","library":"智鼎题库","category":"图片套题","subCategory":"智鼎重点2/套题2","setName":"智鼎重点2 / 套题2","originalFile":"48.jpg","originalPath":"智鼎题库/图片真题/智鼎重点2/套题2/48.jpg","sourceRefs":[{"archive":"智鼎题库.zip","path":"智鼎题库/图片真题/智鼎重点2/套题2/48.jpg","originalFile":"48.jpg","questionNumber":"48"},{"archive":"林木互联网校招笔试题库.zip","path":"林木互联网校招笔试题库/智鼎题库/图片真题/智鼎重点2/套题2/48.jpg","originalFile":"48.jpg","questionNumber":"48"}],"questionType":"image-only","question":"智鼎重点2 / 套题2 第 48 题（整题截图）","options":[],"answer":[],"analysis":"本题为整题截图资料，截图可能包含答案标记；仅用于搜题定位、收藏、背题浏览和后续人工结构化，不进入每日计划、随机练习、模块刷题或模拟考试。","images":["assets/questions/智鼎重点2-套题2-cd1af1d1/048-a836d20292.jpg"],"ocrText":"","tags":["图片题","整题截图","待OCR","智鼎重点2 / 套题2","答案外露","仅资料查看"],"importConfidence":0.45,"needsOcr":true,"answerRevealed":true,"practiceMode":"reference-only","practiceEligible":false,"answerLeakReason":"整题截图可能包含已勾选或高亮答案，不能用于先答题后看答案的普通练习。"},{"id":"q-img-d88c3b3704920982a9","source":"智鼎题库","library":"智鼎题库","category":"图片套题","subCategory":"智鼎重点2/套题2","setName":"智鼎重点2 / 套题2","originalFile":"49.png","originalPath":"智鼎题库/图片真题/智鼎重点2/套题2/49.png","sourceRefs":[{"archive":"智鼎题库.zip","path":"智鼎题库/图片真题/智鼎重点2/套题2/49.png","originalFile":"49.png","questionNumber":"49"},{"archive":"林木互联网校招笔试题库.zip","path":"林木互联网校招笔试题库/智鼎题库/图片真题/智鼎重点2/套题2/49.png","originalFile":"49.png","questionNumber":"49"}],"questionType":"image-only","question":"智鼎重点2 / 套题2 第 49 题（整题截图）","options":[],"answer":[],"analysis":"本题为整题截图资料，截图可能包含答案标记；仅用于搜题定位、收藏、背题浏览和后续人工结构化，不进入每日计划、随机练习、模块刷题或模拟考试。","images":["assets/questions/智鼎重点2-套题2-cd1af1d1/049-abeee70210.png"],"ocrText":"","tags":["图片题","整题截图","待OCR","智鼎重点2 / 套题2","答案外露","仅资料查看"],"importConfidence":0.45,"needsOcr":true,"answerRevealed":true,"practiceMode":"reference-only","practiceEligible":false,"answerLeakReason":"整题截图可能包含已勾选或高亮答案，不能用于先答题后看答案的普通练习。"},{"id":"q-img-4c0fdeb8e308a2543e","source":"智鼎题库","library":"智鼎题库","category":"图片套题","subCategory":"智鼎重点2/套题2","setName":"智鼎重点2 / 套题2","originalFile":"50.jpg","originalPath":"智鼎题库/图片真题/智鼎重点2/套题2/50.jpg","sourceRefs":[{"archive":"智鼎题库.zip","path":"智鼎题库/图片真题/智鼎重点2/套题2/50.jpg","originalFile":"50.jpg","questionNumber":"50"},{"archive":"林木互联网校招笔试题库.zip","path":"林木互联网校招笔试题库/智鼎题库/图片真题/智鼎重点2/套题2/50.jpg","originalFile":"50.jpg","questionNumber":"50"}],"questionType":"image-only","question":"智鼎重点2 / 套题2 第 50 题（整题截图）","options":[],"answer":[],"analysis":"本题为整题截图资料，截图可能包含答案标记；仅用于搜题定位、收藏、背题浏览和后续人工结构化，不进入每日计划、随机练习、模块刷题或模拟考试。","images":["assets/questions/智鼎重点2-套题2-cd1af1d1/050-25f8db825c.jpg"],"ocrText":"","tags":["图片题","整题截图","待OCR","智鼎重点2 / 套题2","答案外露","仅资料查看"],"importConfidence":0.45,"needsOcr":true,"answerRevealed":true,"practiceMode":"reference-only","practiceEligible":false,"answerLeakReason":"整题截图可能包含已勾选或高亮答案，不能用于先答题后看答案的普通练习。"},{"id":"q-img-b86c80ec055c1055a9","source":"智鼎题库","library":"智鼎题库","category":"图片套题","subCategory":"智鼎重点2/套题2","setName":"智鼎重点2 / 套题2","originalFile":"51.jpg","originalPath":"智鼎题库/图片真题/智鼎重点2/套题2/51.jpg","sourceRefs":[{"archive":"智鼎题库.zip","path":"智鼎题库/图片真题/智鼎重点2/套题2/51.jpg","originalFile":"51.jpg","questionNumber":"51"},{"archive":"林木互联网校招笔试题库.zip","path":"林木互联网校招笔试题库/智鼎题库/图片真题/智鼎重点2/套题2/51.jpg","originalFile":"51.jpg","questionNumber":"51"}],"questionType":"image-only","question":"智鼎重点2 / 套题2 第 51 题（整题截图）","options":[],"answer":[],"analysis":"本题为整题截图资料，截图可能包含答案标记；仅用于搜题定位、收藏、背题浏览和后续人工结构化，不进入每日计划、随机练习、模块刷题或模拟考试。","images":["assets/questions/智鼎重点2-套题2-cd1af1d1/051-bac7c8c91e.jpg"],"ocrText":"","tags":["图片题","整题截图","待OCR","智鼎重点2 / 套题2","答案外露","仅资料查看"],"importConfidence":0.45,"needsOcr":true,"answerRevealed":true,"practiceMode":"reference-only","practiceEligible":false,"answerLeakReason":"整题截图可能包含已勾选或高亮答案，不能用于先答题后看答案的普通练习。"},{"id":"q-img-0225a6b7fd55464524","source":"智鼎题库","library":"智鼎题库","category":"图片套题","subCategory":"智鼎重点2/套题2","setName":"智鼎重点2 / 套题2","originalFile":"52.jpg","originalPath":"智鼎题库/图片真题/智鼎重点2/套题2/52.jpg","sourceRefs":[{"archive":"智鼎题库.zip","path":"智鼎题库/图片真题/智鼎重点2/套题2/52.jpg","originalFile":"52.jpg","questionNumber":"52"},{"archive":"林木互联网校招笔试题库.zip","path":"林木互联网校招笔试题库/智鼎题库/图片真题/智鼎重点2/套题2/52.jpg","originalFile":"52.jpg","questionNumber":"52"}],"questionType":"image-only","question":"智鼎重点2 / 套题2 第 52 题（整题截图）","options":[],"answer":[],"analysis":"本题为整题截图资料，截图可能包含答案标记；仅用于搜题定位、收藏、背题浏览和后续人工结构化，不进入每日计划、随机练习、模块刷题或模拟考试。","images":["assets/questions/智鼎重点2-套题2-cd1af1d1/052-7c34b94674.jpg"],"ocrText":"","tags":["图片题","整题截图","待OCR","智鼎重点2 / 套题2","答案外露","仅资料查看"],"importConfidence":0.45,"needsOcr":true,"answerRevealed":true,"practiceMode":"reference-only","practiceEligible":false,"answerLeakReason":"整题截图可能包含已勾选或高亮答案，不能用于先答题后看答案的普通练习。"},{"id":"q-img-32a18e1e712be638ba","source":"智鼎题库","library":"智鼎题库","category":"图片套题","subCategory":"智鼎重点2/套题2","setName":"智鼎重点2 / 套题2","originalFile":"53.jpg","originalPath":"智鼎题库/图片真题/智鼎重点2/套题2/53.jpg","sourceRefs":[{"archive":"智鼎题库.zip","path":"智鼎题库/图片真题/智鼎重点2/套题2/53.jpg","originalFile":"53.jpg","questionNumber":"53"},{"archive":"林木互联网校招笔试题库.zip","path":"林木互联网校招笔试题库/智鼎题库/图片真题/智鼎重点2/套题2/53.jpg","originalFile":"53.jpg","questionNumber":"53"}],"questionType":"image-only","question":"智鼎重点2 / 套题2 第 53 题（整题截图）","options":[],"answer":[],"analysis":"本题为整题截图资料，截图可能包含答案标记；仅用于搜题定位、收藏、背题浏览和后续人工结构化，不进入每日计划、随机练习、模块刷题或模拟考试。","images":["assets/questions/智鼎重点2-套题2-cd1af1d1/053-6785613bd4.jpg"],"ocrText":"","tags":["图片题","整题截图","待OCR","智鼎重点2 / 套题2","答案外露","仅资料查看"],"importConfidence":0.45,"needsOcr":true,"answerRevealed":true,"practiceMode":"reference-only","practiceEligible":false,"answerLeakReason":"整题截图可能包含已勾选或高亮答案，不能用于先答题后看答案的普通练习。"},{"id":"q-img-cc0820c97c649ab3e3","source":"智鼎题库","library":"智鼎题库","category":"图片套题","subCategory":"智鼎重点2/套题2","setName":"智鼎重点2 / 套题2","originalFile":"54.jpg","originalPath":"智鼎题库/图片真题/智鼎重点2/套题2/54.jpg","sourceRefs":[{"archive":"智鼎题库.zip","path":"智鼎题库/图片真题/智鼎重点2/套题2/54.jpg","originalFile":"54.jpg","questionNumber":"54"},{"archive":"林木互联网校招笔试题库.zip","path":"林木互联网校招笔试题库/智鼎题库/图片真题/智鼎重点2/套题2/54.jpg","originalFile":"54.jpg","questionNumber":"54"}],"questionType":"image-only","question":"智鼎重点2 / 套题2 第 54 题（整题截图）","options":[],"answer":[],"analysis":"本题为整题截图资料，截图可能包含答案标记；仅用于搜题定位、收藏、背题浏览和后续人工结构化，不进入每日计划、随机练习、模块刷题或模拟考试。","images":["assets/questions/智鼎重点2-套题2-cd1af1d1/054-abb726900b.jpg"],"ocrText":"","tags":["图片题","整题截图","待OCR","智鼎重点2 / 套题2","答案外露","仅资料查看"],"importConfidence":0.45,"needsOcr":true,"answerRevealed":true,"practiceMode":"reference-only","practiceEligible":false,"answerLeakReason":"整题截图可能包含已勾选或高亮答案，不能用于先答题后看答案的普通练习。"},{"id":"q-img-028ea05abf8f4e9111","source":"智鼎题库","library":"智鼎题库","category":"图片套题","subCategory":"智鼎重点2/套题2","setName":"智鼎重点2 / 套题2","originalFile":"55.jpg","originalPath":"智鼎题库/图片真题/智鼎重点2/套题2/55.jpg","sourceRefs":[{"archive":"智鼎题库.zip","path":"智鼎题库/图片真题/智鼎重点2/套题2/55.jpg","originalFile":"55.jpg","questionNumber":"55"},{"archive":"林木互联网校招笔试题库.zip","path":"林木互联网校招笔试题库/智鼎题库/图片真题/智鼎重点2/套题2/55.jpg","originalFile":"55.jpg","questionNumber":"55"}],"questionType":"image-only","question":"智鼎重点2 / 套题2 第 55 题（整题截图）","options":[],"answer":[],"analysis":"本题为整题截图资料，截图可能包含答案标记；仅用于搜题定位、收藏、背题浏览和后续人工结构化，不进入每日计划、随机练习、模块刷题或模拟考试。","images":["assets/questions/智鼎重点2-套题2-cd1af1d1/055-17072d9c40.jpg"],"ocrText":"","tags":["图片题","整题截图","待OCR","智鼎重点2 / 套题2","答案外露","仅资料查看"],"importConfidence":0.45,"needsOcr":true,"answerRevealed":true,"practiceMode":"reference-only","practiceEligible":false,"answerLeakReason":"整题截图可能包含已勾选或高亮答案，不能用于先答题后看答案的普通练习。"},{"id":"q-img-0e58f582a4cb0f1f75","source":"智鼎题库","library":"智鼎题库","category":"图片套题","subCategory":"智鼎重点2/套题2","setName":"智鼎重点2 / 套题2","originalFile":"56.png","originalPath":"智鼎题库/图片真题/智鼎重点2/套题2/56.png","sourceRefs":[{"archive":"智鼎题库.zip","path":"智鼎题库/图片真题/智鼎重点2/套题2/56.png","originalFile":"56.png","questionNumber":"56"},{"archive":"林木互联网校招笔试题库.zip","path":"林木互联网校招笔试题库/智鼎题库/图片真题/智鼎重点2/套题2/56.png","originalFile":"56.png","questionNumber":"56"}],"questionType":"image-only","question":"智鼎重点2 / 套题2 第 56 题（整题截图）","options":[],"answer":[],"analysis":"本题为整题截图资料，截图可能包含答案标记；仅用于搜题定位、收藏、背题浏览和后续人工结构化，不进入每日计划、随机练习、模块刷题或模拟考试。","images":["assets/questions/智鼎重点2-套题2-cd1af1d1/056-3957581dd6.png"],"ocrText":"","tags":["图片题","整题截图","待OCR","智鼎重点2 / 套题2","答案外露","仅资料查看"],"importConfidence":0.45,"needsOcr":true,"answerRevealed":true,"practiceMode":"reference-only","practiceEligible":false,"answerLeakReason":"整题截图可能包含已勾选或高亮答案，不能用于先答题后看答案的普通练习。"},{"id":"q-img-041a95c98a4a2811d6","source":"智鼎题库","library":"智鼎题库","category":"图片套题","subCategory":"智鼎重点2/套题2","setName":"智鼎重点2 / 套题2","originalFile":"57.png","originalPath":"智鼎题库/图片真题/智鼎重点2/套题2/57.png","sourceRefs":[{"archive":"智鼎题库.zip","path":"智鼎题库/图片真题/智鼎重点2/套题2/57.png","originalFile":"57.png","questionNumber":"57"},{"archive":"林木互联网校招笔试题库.zip","path":"林木互联网校招笔试题库/智鼎题库/图片真题/智鼎重点2/套题2/57.png","originalFile":"57.png","questionNumber":"57"}],"questionType":"image-only","question":"智鼎重点2 / 套题2 第 57 题（整题截图）","options":[],"answer":[],"analysis":"本题为整题截图资料，截图可能包含答案标记；仅用于搜题定位、收藏、背题浏览和后续人工结构化，不进入每日计划、随机练习、模块刷题或模拟考试。","images":["assets/questions/智鼎重点2-套题2-cd1af1d1/057-02c9796cde.png"],"ocrText":"","tags":["图片题","整题截图","待OCR","智鼎重点2 / 套题2","答案外露","仅资料查看"],"importConfidence":0.45,"needsOcr":true,"answerRevealed":true,"practiceMode":"reference-only","practiceEligible":false,"answerLeakReason":"整题截图可能包含已勾选或高亮答案，不能用于先答题后看答案的普通练习。"},{"id":"q-img-11d23117e4d26d3d5e","source":"智鼎题库","library":"智鼎题库","category":"图片套题","subCategory":"智鼎重点2/套题2","setName":"智鼎重点2 / 套题2","originalFile":"58.png","originalPath":"智鼎题库/图片真题/智鼎重点2/套题2/58.png","sourceRefs":[{"archive":"智鼎题库.zip","path":"智鼎题库/图片真题/智鼎重点2/套题2/58.png","originalFile":"58.png","questionNumber":"58"},{"archive":"林木互联网校招笔试题库.zip","path":"林木互联网校招笔试题库/智鼎题库/图片真题/智鼎重点2/套题2/58.png","originalFile":"58.png","questionNumber":"58"}],"questionType":"image-only","question":"智鼎重点2 / 套题2 第 58 题（整题截图）","options":[],"answer":[],"analysis":"本题为整题截图资料，截图可能包含答案标记；仅用于搜题定位、收藏、背题浏览和后续人工结构化，不进入每日计划、随机练习、模块刷题或模拟考试。","images":["assets/questions/智鼎重点2-套题2-cd1af1d1/058-dcb47116c0.png"],"ocrText":"","tags":["图片题","整题截图","待OCR","智鼎重点2 / 套题2","答案外露","仅资料查看"],"importConfidence":0.45,"needsOcr":true,"answerRevealed":true,"practiceMode":"reference-only","practiceEligible":false,"answerLeakReason":"整题截图可能包含已勾选或高亮答案，不能用于先答题后看答案的普通练习。"},{"id":"q-img-38237e517408869676","source":"智鼎题库","library":"智鼎题库","category":"图片套题","subCategory":"智鼎重点2/套题2","setName":"智鼎重点2 / 套题2","originalFile":"59.png","originalPath":"智鼎题库/图片真题/智鼎重点2/套题2/59.png","sourceRefs":[{"archive":"智鼎题库.zip","path":"智鼎题库/图片真题/智鼎重点2/套题2/59.png","originalFile":"59.png","questionNumber":"59"},{"archive":"林木互联网校招笔试题库.zip","path":"林木互联网校招笔试题库/智鼎题库/图片真题/智鼎重点2/套题2/59.png","originalFile":"59.png","questionNumber":"59"}],"questionType":"image-only","question":"智鼎重点2 / 套题2 第 59 题（整题截图）","options":[],"answer":[],"analysis":"本题为整题截图资料，截图可能包含答案标记；仅用于搜题定位、收藏、背题浏览和后续人工结构化，不进入每日计划、随机练习、模块刷题或模拟考试。","images":["assets/questions/智鼎重点2-套题2-cd1af1d1/059-ee647198f2.png"],"ocrText":"","tags":["图片题","整题截图","待OCR","智鼎重点2 / 套题2","答案外露","仅资料查看"],"importConfidence":0.45,"needsOcr":true,"answerRevealed":true,"practiceMode":"reference-only","practiceEligible":false,"answerLeakReason":"整题截图可能包含已勾选或高亮答案，不能用于先答题后看答案的普通练习。"},{"id":"q-img-a7998ac98bd7aa5548","source":"智鼎题库","library":"智鼎题库","category":"图片套题","subCategory":"智鼎重点2/套题2","setName":"智鼎重点2 / 套题2","originalFile":"60.png","originalPath":"智鼎题库/图片真题/智鼎重点2/套题2/60.png","sourceRefs":[{"archive":"智鼎题库.zip","path":"智鼎题库/图片真题/智鼎重点2/套题2/60.png","originalFile":"60.png","questionNumber":"60"},{"archive":"林木互联网校招笔试题库.zip","path":"林木互联网校招笔试题库/智鼎题库/图片真题/智鼎重点2/套题2/60.png","originalFile":"60.png","questionNumber":"60"}],"questionType":"image-only","question":"智鼎重点2 / 套题2 第 60 题（整题截图）","options":[],"answer":[],"analysis":"本题为整题截图资料，截图可能包含答案标记；仅用于搜题定位、收藏、背题浏览和后续人工结构化，不进入每日计划、随机练习、模块刷题或模拟考试。","images":["assets/questions/智鼎重点2-套题2-cd1af1d1/060-6e93a06d27.png"],"ocrText":"","tags":["图片题","整题截图","待OCR","智鼎重点2 / 套题2","答案外露","仅资料查看"],"importConfidence":0.45,"needsOcr":true,"answerRevealed":true,"practiceMode":"reference-only","practiceEligible":false,"answerLeakReason":"整题截图可能包含已勾选或高亮答案，不能用于先答题后看答案的普通练习。"},{"id":"q-img-4b6a6f8f1b6ec9fea1","source":"智鼎题库","library":"智鼎题库","category":"图片套题","subCategory":"智鼎重点2/套题2","setName":"智鼎重点2 / 套题2","originalFile":"61.png","originalPath":"智鼎题库/图片真题/智鼎重点2/套题2/61.png","sourceRefs":[{"archive":"智鼎题库.zip","path":"智鼎题库/图片真题/智鼎重点2/套题2/61.png","originalFile":"61.png","questionNumber":"61"},{"archive":"林木互联网校招笔试题库.zip","path":"林木互联网校招笔试题库/智鼎题库/图片真题/智鼎重点2/套题2/61.png","originalFile":"61.png","questionNumber":"61"}],"questionType":"image-only","question":"智鼎重点2 / 套题2 第 61 题（整题截图）","options":[],"answer":[],"analysis":"本题为整题截图资料，截图可能包含答案标记；仅用于搜题定位、收藏、背题浏览和后续人工结构化，不进入每日计划、随机练习、模块刷题或模拟考试。","images":["assets/questions/智鼎重点2-套题2-cd1af1d1/061-d9ef10cb03.png"],"ocrText":"","tags":["图片题","整题截图","待OCR","智鼎重点2 / 套题2","答案外露","仅资料查看"],"importConfidence":0.45,"needsOcr":true,"answerRevealed":true,"practiceMode":"reference-only","practiceEligible":false,"answerLeakReason":"整题截图可能包含已勾选或高亮答案，不能用于先答题后看答案的普通练习。"},{"id":"q-img-5ce14f13593e4b3933","source":"智鼎题库","library":"智鼎题库","category":"图片套题","subCategory":"智鼎重点2/套题2","setName":"智鼎重点2 / 套题2","originalFile":"62.png","originalPath":"智鼎题库/图片真题/智鼎重点2/套题2/62.png","sourceRefs":[{"archive":"智鼎题库.zip","path":"智鼎题库/图片真题/智鼎重点2/套题2/62.png","originalFile":"62.png","questionNumber":"62"},{"archive":"林木互联网校招笔试题库.zip","path":"林木互联网校招笔试题库/智鼎题库/图片真题/智鼎重点2/套题2/62.png","originalFile":"62.png","questionNumber":"62"}],"questionType":"image-only","question":"智鼎重点2 / 套题2 第 62 题（整题截图）","options":[],"answer":[],"analysis":"本题为整题截图资料，截图可能包含答案标记；仅用于搜题定位、收藏、背题浏览和后续人工结构化，不进入每日计划、随机练习、模块刷题或模拟考试。","images":["assets/questions/智鼎重点2-套题2-cd1af1d1/062-9885f61406.png"],"ocrText":"","tags":["图片题","整题截图","待OCR","智鼎重点2 / 套题2","答案外露","仅资料查看"],"importConfidence":0.45,"needsOcr":true,"answerRevealed":true,"practiceMode":"reference-only","practiceEligible":false,"answerLeakReason":"整题截图可能包含已勾选或高亮答案，不能用于先答题后看答案的普通练习。"},{"id":"q-img-e6a83a781301ed713a","source":"智鼎题库","library":"智鼎题库","category":"图片套题","subCategory":"智鼎重点2/套题2","setName":"智鼎重点2 / 套题2","originalFile":"63.png","originalPath":"智鼎题库/图片真题/智鼎重点2/套题2/63.png","sourceRefs":[{"archive":"智鼎题库.zip","path":"智鼎题库/图片真题/智鼎重点2/套题2/63.png","originalFile":"63.png","questionNumber":"63"},{"archive":"林木互联网校招笔试题库.zip","path":"林木互联网校招笔试题库/智鼎题库/图片真题/智鼎重点2/套题2/63.png","originalFile":"63.png","questionNumber":"63"}],"questionType":"image-only","question":"智鼎重点2 / 套题2 第 63 题（整题截图）","options":[],"answer":[],"analysis":"本题为整题截图资料，截图可能包含答案标记；仅用于搜题定位、收藏、背题浏览和后续人工结构化，不进入每日计划、随机练习、模块刷题或模拟考试。","images":["assets/questions/智鼎重点2-套题2-cd1af1d1/063-594d2ecce9.png"],"ocrText":"","tags":["图片题","整题截图","待OCR","智鼎重点2 / 套题2","答案外露","仅资料查看"],"importConfidence":0.45,"needsOcr":true,"answerRevealed":true,"practiceMode":"reference-only","practiceEligible":false,"answerLeakReason":"整题截图可能包含已勾选或高亮答案，不能用于先答题后看答案的普通练习。"},{"id":"q-img-6ccc414507e8da350f","source":"智鼎题库","library":"智鼎题库","category":"图片套题","subCategory":"智鼎重点2/套题2","setName":"智鼎重点2 / 套题2","originalFile":"64.png","originalPath":"智鼎题库/图片真题/智鼎重点2/套题2/64.png","sourceRefs":[{"archive":"智鼎题库.zip","path":"智鼎题库/图片真题/智鼎重点2/套题2/64.png","originalFile":"64.png","questionNumber":"64"},{"archive":"林木互联网校招笔试题库.zip","path":"林木互联网校招笔试题库/智鼎题库/图片真题/智鼎重点2/套题2/64.png","originalFile":"64.png","questionNumber":"64"}],"questionType":"image-only","question":"智鼎重点2 / 套题2 第 64 题（整题截图）","options":[],"answer":[],"analysis":"本题为整题截图资料，截图可能包含答案标记；仅用于搜题定位、收藏、背题浏览和后续人工结构化，不进入每日计划、随机练习、模块刷题或模拟考试。","images":["assets/questions/智鼎重点2-套题2-cd1af1d1/064-428fbe0fe0.png"],"ocrText":"","tags":["图片题","整题截图","待OCR","智鼎重点2 / 套题2","答案外露","仅资料查看"],"importConfidence":0.45,"needsOcr":true,"answerRevealed":true,"practiceMode":"reference-only","practiceEligible":false,"answerLeakReason":"整题截图可能包含已勾选或高亮答案，不能用于先答题后看答案的普通练习。"},{"id":"q-img-2f08e01038ee9f09ac","source":"智鼎题库","library":"智鼎题库","category":"图片套题","subCategory":"智鼎重点2/套题2","setName":"智鼎重点2 / 套题2","originalFile":"65.jpg","originalPath":"智鼎题库/图片真题/智鼎重点2/套题2/65.jpg","sourceRefs":[{"archive":"智鼎题库.zip","path":"智鼎题库/图片真题/智鼎重点2/套题2/65.jpg","originalFile":"65.jpg","questionNumber":"65"},{"archive":"林木互联网校招笔试题库.zip","path":"林木互联网校招笔试题库/智鼎题库/图片真题/智鼎重点2/套题2/65.jpg","originalFile":"65.jpg","questionNumber":"65"}],"questionType":"image-only","question":"智鼎重点2 / 套题2 第 65 题（整题截图）","options":[],"answer":[],"analysis":"本题为整题截图资料，截图可能包含答案标记；仅用于搜题定位、收藏、背题浏览和后续人工结构化，不进入每日计划、随机练习、模块刷题或模拟考试。","images":["assets/questions/智鼎重点2-套题2-cd1af1d1/065-30aae94540.jpg"],"ocrText":"","tags":["图片题","整题截图","待OCR","智鼎重点2 / 套题2","答案外露","仅资料查看"],"importConfidence":0.45,"needsOcr":true,"answerRevealed":true,"practiceMode":"reference-only","practiceEligible":false,"answerLeakReason":"整题截图可能包含已勾选或高亮答案，不能用于先答题后看答案的普通练习。"},{"id":"q-img-75d457b0002e25c260","source":"智鼎题库","library":"智鼎题库","category":"图片套题","subCategory":"智鼎重点2/套题2","setName":"智鼎重点2 / 套题2","originalFile":"66.png","originalPath":"智鼎题库/图片真题/智鼎重点2/套题2/66.png","sourceRefs":[{"archive":"智鼎题库.zip","path":"智鼎题库/图片真题/智鼎重点2/套题2/66.png","originalFile":"66.png","questionNumber":"66"},{"archive":"林木互联网校招笔试题库.zip","path":"林木互联网校招笔试题库/智鼎题库/图片真题/智鼎重点2/套题2/66.png","originalFile":"66.png","questionNumber":"66"}],"questionType":"image-only","question":"智鼎重点2 / 套题2 第 66 题（整题截图）","options":[],"answer":[],"analysis":"本题为整题截图资料，截图可能包含答案标记；仅用于搜题定位、收藏、背题浏览和后续人工结构化，不进入每日计划、随机练习、模块刷题或模拟考试。","images":["assets/questions/智鼎重点2-套题2-cd1af1d1/066-5a6216f291.png"],"ocrText":"","tags":["图片题","整题截图","待OCR","智鼎重点2 / 套题2","答案外露","仅资料查看"],"importConfidence":0.45,"needsOcr":true,"answerRevealed":true,"practiceMode":"reference-only","practiceEligible":false,"answerLeakReason":"整题截图可能包含已勾选或高亮答案，不能用于先答题后看答案的普通练习。"},{"id":"q-img-c073bcb1e8b476640d","source":"智鼎题库","library":"智鼎题库","category":"图片套题","subCategory":"智鼎重点2/套题2","setName":"智鼎重点2 / 套题2","originalFile":"67.jpg","originalPath":"智鼎题库/图片真题/智鼎重点2/套题2/67.jpg","sourceRefs":[{"archive":"智鼎题库.zip","path":"智鼎题库/图片真题/智鼎重点2/套题2/67.jpg","originalFile":"67.jpg","questionNumber":"67"},{"archive":"林木互联网校招笔试题库.zip","path":"林木互联网校招笔试题库/智鼎题库/图片真题/智鼎重点2/套题2/67.jpg","originalFile":"67.jpg","questionNumber":"67"}],"questionType":"image-only","question":"智鼎重点2 / 套题2 第 67 题（整题截图）","options":[],"answer":[],"analysis":"本题为整题截图资料，截图可能包含答案标记；仅用于搜题定位、收藏、背题浏览和后续人工结构化，不进入每日计划、随机练习、模块刷题或模拟考试。","images":["assets/questions/智鼎重点2-套题2-cd1af1d1/067-2eb5f754c9.jpg"],"ocrText":"","tags":["图片题","整题截图","待OCR","智鼎重点2 / 套题2","答案外露","仅资料查看"],"importConfidence":0.45,"needsOcr":true,"answerRevealed":true,"practiceMode":"reference-only","practiceEligible":false,"answerLeakReason":"整题截图可能包含已勾选或高亮答案，不能用于先答题后看答案的普通练习。"},{"id":"q-img-33a51c9a2224e5b72a","source":"智鼎题库","library":"智鼎题库","category":"图片套题","subCategory":"智鼎重点2/套题2","setName":"智鼎重点2 / 套题2","originalFile":"68.png","originalPath":"智鼎题库/图片真题/智鼎重点2/套题2/68.png","sourceRefs":[{"archive":"智鼎题库.zip","path":"智鼎题库/图片真题/智鼎重点2/套题2/68.png","originalFile":"68.png","questionNumber":"68"},{"archive":"林木互联网校招笔试题库.zip","path":"林木互联网校招笔试题库/智鼎题库/图片真题/智鼎重点2/套题2/68.png","originalFile":"68.png","questionNumber":"68"}],"questionType":"image-only","question":"智鼎重点2 / 套题2 第 68 题（整题截图）","options":[],"answer":[],"analysis":"本题为整题截图资料，截图可能包含答案标记；仅用于搜题定位、收藏、背题浏览和后续人工结构化，不进入每日计划、随机练习、模块刷题或模拟考试。","images":["assets/questions/智鼎重点2-套题2-cd1af1d1/068-45808c1691.png"],"ocrText":"","tags":["图片题","整题截图","待OCR","智鼎重点2 / 套题2","答案外露","仅资料查看"],"importConfidence":0.45,"needsOcr":true,"answerRevealed":true,"practiceMode":"reference-only","practiceEligible":false,"answerLeakReason":"整题截图可能包含已勾选或高亮答案，不能用于先答题后看答案的普通练习。"},{"id":"q-img-6e798c64b39e7e3d56","source":"智鼎题库","library":"智鼎题库","category":"图片套题","subCategory":"智鼎重点2/套题2","setName":"智鼎重点2 / 套题2","originalFile":"69.png","originalPath":"智鼎题库/图片真题/智鼎重点2/套题2/69.png","sourceRefs":[{"archive":"智鼎题库.zip","path":"智鼎题库/图片真题/智鼎重点2/套题2/69.png","originalFile":"69.png","questionNumber":"69"},{"archive":"林木互联网校招笔试题库.zip","path":"林木互联网校招笔试题库/智鼎题库/图片真题/智鼎重点2/套题2/69.png","originalFile":"69.png","questionNumber":"69"}],"questionType":"image-only","question":"智鼎重点2 / 套题2 第 69 题（整题截图）","options":[],"answer":[],"analysis":"本题为整题截图资料，截图可能包含答案标记；仅用于搜题定位、收藏、背题浏览和后续人工结构化，不进入每日计划、随机练习、模块刷题或模拟考试。","images":["assets/questions/智鼎重点2-套题2-cd1af1d1/069-3e48fb4e9d.png"],"ocrText":"","tags":["图片题","整题截图","待OCR","智鼎重点2 / 套题2","答案外露","仅资料查看"],"importConfidence":0.45,"needsOcr":true,"answerRevealed":true,"practiceMode":"reference-only","practiceEligible":false,"answerLeakReason":"整题截图可能包含已勾选或高亮答案，不能用于先答题后看答案的普通练习。"}]