[{"id":"q-remaining-0d5b7b5fe46f74d0cb","source":"北森题库","library":"北森题库","category":"数学运算","subCategory":"北森题库/24北森/其他/通用行测","setName":"通用行测各类题型汇总及参考答案","originalFile":"通用行测各类题型汇总及参考答案.pdf","originalPath":"北森题库/24北森/其他/通用行测各类题型汇总及参考答案.pdf","sourceRefs":[{"archive":"北森题库.zip","path":"北森题库/24北森/其他/通用行测各类题型汇总及参考答案.pdf","originalFile":"通用行测各类题型汇总及参考答案.pdf","questionNumber":"","pdfPage":738}],"questionType":"single","question":"4，27，16，25，36，23，64，21，（ ）。","options":[{"key":"A","text":"81"},{"key":"B","text":"100"},{"key":"C","text":"121"},{"key":"D","text":"19"}],"answer":["B"],"analysis":"奇数项是：4,16,36,64 属于幂次数列，偶数项是 27，25,23,21，所以下一项应该是 102=100。 所以选 B。","images":[],"imageRefs":[],"ocrText":"","tags":["数学运算","通用行测"],"importConfidence":0.93,"importNotes":["remaining_pdf_structured_import","remaining_pdf_explicit_answer_marker","remaining_pdf_page_traced"],"practiceMode":"practice","practiceEligible":true,"reviewOnly":false},{"id":"q-remaining-181a939fa001a2074e","source":"北森题库","library":"北森题库","category":"数学运算","subCategory":"北森题库/24北森/其他/通用行测","setName":"通用行测各类题型汇总及参考答案","originalFile":"通用行测各类题型汇总及参考答案.pdf","originalPath":"北森题库/24北森/其他/通用行测各类题型汇总及参考答案.pdf","sourceRefs":[{"archive":"北森题库.zip","path":"北森题库/24北森/其他/通用行测各类题型汇总及参考答案.pdf","originalFile":"通用行测各类题型汇总及参考答案.pdf","questionNumber":"","pdfPage":738}],"questionType":"single","question":"4，4，16，144，（ ）","options":[{"key":"A","text":"162"},{"key":"B","text":"2304"},{"key":"C","text":"242"},{"key":"D","text":"512"}],"answer":["B"],"analysis":"通过观察， 可以发现数列有以下特点：4×12=4，4×22=16，16×32= 144， 即符 合：An×n2=An+1。 所以选项=144×42=2304。因此，本题答案选择 B 选项。 【尾数法】","images":[],"imageRefs":[],"ocrText":"","tags":["数学运算","通用行测"],"importConfidence":0.93,"importNotes":["remaining_pdf_structured_import","remaining_pdf_explicit_answer_marker","remaining_pdf_page_traced"],"practiceMode":"practice","practiceEligible":true,"reviewOnly":false},{"id":"q-remaining-18da198defdbc70840","source":"北森题库","library":"北森题库","category":"数学运算","subCategory":"北森题库/24北森/其他/通用行测","setName":"通用行测各类题型汇总及参考答案","originalFile":"通用行测各类题型汇总及参考答案.pdf","originalPath":"北森题库/24北森/其他/通用行测各类题型汇总及参考答案.pdf","sourceRefs":[{"archive":"北森题库.zip","path":"北森题库/24北森/其他/通用行测各类题型汇总及参考答案.pdf","originalFile":"通用行测各类题型汇总及参考答案.pdf","questionNumber":"","pdfPage":738}],"questionType":"single","question":"4，4，4，8，24，120，( )","options":[{"key":"A","text":"240"},{"key":"B","text":"360"},{"key":"C","text":"560"},{"key":"D","text":"960"}],"answer":["D"],"analysis":"考核多级数列，相邻两项两两作商得到二级商数列 1，1，2，3，5，为简单递推和数列，下 一项应为 8，反推括号应为 960，因此答案选择 D 选项。","images":[],"imageRefs":[],"ocrText":"","tags":["数学运算","通用行测"],"importConfidence":0.93,"importNotes":["remaining_pdf_structured_import","remaining_pdf_explicit_answer_marker","remaining_pdf_page_traced"],"practiceMode":"practice","practiceEligible":true,"reviewOnly":false},{"id":"q-remaining-65d1fbc73f843d3b33","source":"北森题库","library":"北森题库","category":"数学运算","subCategory":"北森题库/24北森/其他/通用行测","setName":"通用行测各类题型汇总及参考答案","originalFile":"通用行测各类题型汇总及参考答案.pdf","originalPath":"北森题库/24北森/其他/通用行测各类题型汇总及参考答案.pdf","sourceRefs":[{"archive":"北森题库.zip","path":"北森题库/24北森/其他/通用行测各类题型汇总及参考答案.pdf","originalFile":"通用行测各类题型汇总及参考答案.pdf","questionNumber":"","pdfPage":738}],"questionType":"single","question":"4，5，（ ），14，23，37","options":[{"key":"A","text":"6"},{"key":"B","text":"7"},{"key":"C","text":"8"},{"key":"D","text":"9"}],"answer":["D"],"analysis":"4+5=9,5+9=14,9+14=23,14+23=37。因此，本题答案为 D 选项。","images":[],"imageRefs":[],"ocrText":"","tags":["数学运算","通用行测"],"importConfidence":0.93,"importNotes":["remaining_pdf_structured_import","remaining_pdf_explicit_answer_marker","remaining_pdf_page_traced"],"practiceMode":"practice","practiceEligible":true,"reviewOnly":false},{"id":"q-remaining-8cd23f1395e726e9fd","source":"北森题库","library":"北森题库","category":"数学运算","subCategory":"北森题库/24北森/其他/通用行测","setName":"通用行测各类题型汇总及参考答案","originalFile":"通用行测各类题型汇总及参考答案.pdf","originalPath":"北森题库/24北森/其他/通用行测各类题型汇总及参考答案.pdf","sourceRefs":[{"archive":"北森题库.zip","path":"北森题库/24北森/其他/通用行测各类题型汇总及参考答案.pdf","originalFile":"通用行测各类题型汇总及参考答案.pdf","questionNumber":"","pdfPage":739}],"questionType":"single","question":"4，5，7，11，19，（ ）","options":[{"key":"A","text":"27"},{"key":"B","text":"31"},{"key":"C","text":"35"},{"key":"D","text":"41"}],"answer":["C"],"analysis":"原数列做差可得：1、2、4、8。差是一个公比为 2 的等比数列，那么下一个差应该是 16， 原数列的下一个数为 19+16=35。因此，本题答案为 C 选项。","images":[],"imageRefs":[],"ocrText":"","tags":["数学运算","通用行测"],"importConfidence":0.93,"importNotes":["remaining_pdf_structured_import","remaining_pdf_explicit_answer_marker","remaining_pdf_page_traced"],"practiceMode":"practice","practiceEligible":true,"reviewOnly":false},{"id":"q-remaining-0340262bd6ea9da0e9","source":"北森题库","library":"北森题库","category":"数学运算","subCategory":"北森题库/24北森/其他/通用行测","setName":"通用行测各类题型汇总及参考答案","originalFile":"通用行测各类题型汇总及参考答案.pdf","originalPath":"北森题库/24北森/其他/通用行测各类题型汇总及参考答案.pdf","sourceRefs":[{"archive":"北森题库.zip","path":"北森题库/24北森/其他/通用行测各类题型汇总及参考答案.pdf","originalFile":"通用行测各类题型汇总及参考答案.pdf","questionNumber":"","pdfPage":739}],"questionType":"single","question":"4，5，8，10，16，19，32，（ ）。","options":[{"key":"A","text":"35"},{"key":"B","text":"36"},{"key":"C","text":"37"},{"key":"D","text":"38"}],"answer":["B"],"analysis":"每相邻两个一组，二者之差依次是 4-5=-1；8-10=-2；16-19=-3；32-（36）=-4。因此本题答 案 B。","images":[],"imageRefs":[],"ocrText":"","tags":["数学运算","通用行测"],"importConfidence":0.93,"importNotes":["remaining_pdf_structured_import","remaining_pdf_explicit_answer_marker","remaining_pdf_page_traced"],"practiceMode":"practice","practiceEligible":true,"reviewOnly":false},{"id":"q-remaining-61e5c515e191fa473d","source":"北森题库","library":"北森题库","category":"数学运算","subCategory":"北森题库/24北森/其他/通用行测","setName":"通用行测各类题型汇总及参考答案","originalFile":"通用行测各类题型汇总及参考答案.pdf","originalPath":"北森题库/24北森/其他/通用行测各类题型汇总及参考答案.pdf","sourceRefs":[{"archive":"北森题库.zip","path":"北森题库/24北森/其他/通用行测各类题型汇总及参考答案.pdf","originalFile":"通用行测各类题型汇总及参考答案.pdf","questionNumber":"","pdfPage":739}],"questionType":"single","question":"4，6，5，7，7，9，11，13，19，21，（ ），（ ）。","options":[{"key":"A","text":"27，29"},{"key":"B","text":"32，33"},{"key":"C","text":"35，37"},{"key":"D","text":"41，43"}],"answer":["C"],"analysis":"解法一：奇数项 4，5，7， 11，19 ，（35） ，做差为1，2，4，8，16；偶数项 6，7，9，13， 21，（37） ，做差为1，2，4，8，16。因此，本题答案为 C 选项。解法二：两两分组，组内差为2，组内和分别为 10， 12，16，24，40，？，做一次差得 2，4，8，16，32，故？=40+32=72。因此，本题答案为 C 选项。","images":[],"imageRefs":[],"ocrText":"","tags":["数学运算","通用行测"],"importConfidence":0.93,"importNotes":["remaining_pdf_structured_import","remaining_pdf_explicit_answer_marker","remaining_pdf_page_traced"],"practiceMode":"practice","practiceEligible":true,"reviewOnly":false},{"id":"q-remaining-2230862aee916ae01d","source":"北森题库","library":"北森题库","category":"数学运算","subCategory":"北森题库/24北森/其他/通用行测","setName":"通用行测各类题型汇总及参考答案","originalFile":"通用行测各类题型汇总及参考答案.pdf","originalPath":"北森题库/24北森/其他/通用行测各类题型汇总及参考答案.pdf","sourceRefs":[{"archive":"北森题库.zip","path":"北森题库/24北森/其他/通用行测各类题型汇总及参考答案.pdf","originalFile":"通用行测各类题型汇总及参考答案.pdf","questionNumber":"","pdfPage":739}],"questionType":"single","question":"4，7，11，18，29，（ ）。","options":[{"key":"A","text":"37"},{"key":"B","text":"40"},{"key":"C","text":"43"},{"key":"D","text":"47"}],"answer":["D"],"analysis":"由 11=4+7，18=7+11，29=11+18 可知原数列各项满足递推规律， 所以下一项应为18+29=47。 因此，本题答案为 D 选项。","images":[],"imageRefs":[],"ocrText":"","tags":["数学运算","通用行测"],"importConfidence":0.93,"importNotes":["remaining_pdf_structured_import","remaining_pdf_explicit_answer_marker","remaining_pdf_page_traced"],"practiceMode":"practice","practiceEligible":true,"reviewOnly":false},{"id":"q-remaining-b87b817fa6b5891447","source":"北森题库","library":"北森题库","category":"数学运算","subCategory":"北森题库/24北森/其他/通用行测","setName":"通用行测各类题型汇总及参考答案","originalFile":"通用行测各类题型汇总及参考答案.pdf","originalPath":"北森题库/24北森/其他/通用行测各类题型汇总及参考答案.pdf","sourceRefs":[{"archive":"北森题库.zip","path":"北森题库/24北森/其他/通用行测各类题型汇总及参考答案.pdf","originalFile":"通用行测各类题型汇总及参考答案.pdf","questionNumber":"","pdfPage":739}],"questionType":"single","question":"4，8，14，23，36，（ ）。","options":[{"key":"A","text":"49"},{"key":"B","text":"51"},{"key":"C","text":"53"},{"key":"D","text":"54"}],"answer":["D"],"analysis":"由下图，做差两次后所得数列为等差数列，下一项为 5，故 13+ 5=18,36+18=54。所求项为 54。因此，本题答案为 D 选项。","images":[],"imageRefs":[],"ocrText":"","tags":["数学运算","通用行测"],"importConfidence":0.93,"importNotes":["remaining_pdf_structured_import","remaining_pdf_explicit_answer_marker","remaining_pdf_page_traced"],"practiceMode":"practice","practiceEligible":true,"reviewOnly":false},{"id":"q-remaining-6c872a6d3b509b5d01","source":"北森题库","library":"北森题库","category":"数学运算","subCategory":"北森题库/24北森/其他/通用行测","setName":"通用行测各类题型汇总及参考答案","originalFile":"通用行测各类题型汇总及参考答案.pdf","originalPath":"北森题库/24北森/其他/通用行测各类题型汇总及参考答案.pdf","sourceRefs":[{"archive":"北森题库.zip","path":"北森题库/24北森/其他/通用行测各类题型汇总及参考答案.pdf","originalFile":"通用行测各类题型汇总及参考答案.pdf","questionNumber":"","pdfPage":739}],"questionType":"single","question":"4，9 ， 15，26，43，（ ）","options":[{"key":"A","text":"68"},{"key":"B","text":"69"},{"key":"C","text":"70"},{"key":"D","text":"71"}],"answer":["D"],"analysis":"4 ＋9＋2＝15，9＋15＋2＝26，15＋26＋2＝43，（ ）＝26＋43＋2＝71。因此，答案选择 D 选项。","images":[],"imageRefs":[],"ocrText":"","tags":["数学运算","通用行测"],"importConfidence":0.93,"importNotes":["remaining_pdf_structured_import","remaining_pdf_explicit_answer_marker","remaining_pdf_page_traced"],"practiceMode":"practice","practiceEligible":true,"reviewOnly":false},{"id":"q-remaining-d8e65b88b93b1ccee2","source":"北森题库","library":"北森题库","category":"数学运算","subCategory":"北森题库/24北森/其他/通用行测","setName":"通用行测各类题型汇总及参考答案","originalFile":"通用行测各类题型汇总及参考答案.pdf","originalPath":"北森题库/24北森/其他/通用行测各类题型汇总及参考答案.pdf","sourceRefs":[{"archive":"北森题库.zip","path":"北森题库/24北森/其他/通用行测各类题型汇总及参考答案.pdf","originalFile":"通用行测各类题型汇总及参考答案.pdf","questionNumber":"","pdfPage":740}],"questionType":"single","question":"4，9，8，11，12，( )。","options":[{"key":"A","text":"13"},{"key":"B","text":"14"},{"key":"C","text":"17"},{"key":"D","text":"19"}],"answer":["C"],"analysis":"原数列依次做和得到：13，17，19，23，()明显为连续的质数数列， 因此下一项为29。 所以， 所求项为 29－12=17。因此本题正确答案为 C","images":[],"imageRefs":[],"ocrText":"","tags":["数学运算","通用行测"],"importConfidence":0.93,"importNotes":["remaining_pdf_structured_import","remaining_pdf_explicit_answer_marker","remaining_pdf_page_traced"],"practiceMode":"practice","practiceEligible":true,"reviewOnly":false},{"id":"q-remaining-0e81e4436b0ea06528","source":"北森题库","library":"北森题库","category":"数学运算","subCategory":"北森题库/24北森/其他/通用行测","setName":"通用行测各类题型汇总及参考答案","originalFile":"通用行测各类题型汇总及参考答案.pdf","originalPath":"北森题库/24北森/其他/通用行测各类题型汇总及参考答案.pdf","sourceRefs":[{"archive":"北森题库.zip","path":"北森题库/24北森/其他/通用行测各类题型汇总及参考答案.pdf","originalFile":"通用行测各类题型汇总及参考答案.pdf","questionNumber":"","pdfPage":740}],"questionType":"single","question":"40，3，35，6，30，9，（ ），12，20，（ ）。","options":[{"key":"A","text":"15，25"},{"key":"B","text":"18，25"},{"key":"C","text":"25，15"},{"key":"D","text":"25，18"}],"answer":["C"],"analysis":"奇数项为 40，35，30，（25），20 的等差数 列；偶数项为 3， 6，9，12，（15）的等差数列， 所以答案为（25，15） 。因此，本题答案为C 选项。","images":[],"imageRefs":[],"ocrText":"","tags":["数学运算","通用行测"],"importConfidence":0.93,"importNotes":["remaining_pdf_structured_import","remaining_pdf_explicit_answer_marker","remaining_pdf_page_traced"],"practiceMode":"practice","practiceEligible":true,"reviewOnly":false},{"id":"q-remaining-3f85cadcc0e3bbd529","source":"北森题库","library":"北森题库","category":"数学运算","subCategory":"北森题库/24北森/其他/通用行测","setName":"通用行测各类题型汇总及参考答案","originalFile":"通用行测各类题型汇总及参考答案.pdf","originalPath":"北森题库/24北森/其他/通用行测各类题型汇总及参考答案.pdf","sourceRefs":[{"archive":"北森题库.zip","path":"北森题库/24北森/其他/通用行测各类题型汇总及参考答案.pdf","originalFile":"通用行测各类题型汇总及参考答案.pdf","questionNumber":"","pdfPage":740}],"questionType":"single","question":"41，59，32，68，72，（ ）。","options":[{"key":"A","text":"28"},{"key":"B","text":"36"},{"key":"C","text":"40"},{"key":"D","text":"48"}],"answer":["A"],"analysis":"两两分组得到（41，59），（32，68）。（72，( )）,发现组内做和均为 100。因此，本题答案为 A 选项。","images":[],"imageRefs":[],"ocrText":"","tags":["数学运算","通用行测"],"importConfidence":0.93,"importNotes":["remaining_pdf_structured_import","remaining_pdf_explicit_answer_marker","remaining_pdf_page_traced"],"practiceMode":"practice","practiceEligible":true,"reviewOnly":false},{"id":"q-remaining-9a7d5449be458ab2f0","source":"北森题库","library":"北森题库","category":"数学运算","subCategory":"北森题库/24北森/其他/通用行测","setName":"通用行测各类题型汇总及参考答案","originalFile":"通用行测各类题型汇总及参考答案.pdf","originalPath":"北森题库/24北森/其他/通用行测各类题型汇总及参考答案.pdf","sourceRefs":[{"archive":"北森题库.zip","path":"北森题库/24北森/其他/通用行测各类题型汇总及参考答案.pdf","originalFile":"通用行测各类题型汇总及参考答案.pdf","questionNumber":"","pdfPage":740}],"questionType":"single","question":"44，52，59，73，83，94，（ ）。","options":[{"key":"A","text":"107"},{"key":"B","text":"101"},{"key":"C","text":"105"},{"key":"D","text":"113"}],"answer":["A"],"analysis":"通过观察数列， 可以发现：52＝44+4+4，59＝52+5+2，73＝59+5+9，83＝73+7+3，94＝83+8+3， 即后一项=前一项+前一项的个位— +前一项的十位，所以选项=94+9+4＝107。因此，本题答案选择 A 选项。","images":[],"imageRefs":[],"ocrText":"","tags":["数学运算","通用行测"],"importConfidence":0.93,"importNotes":["remaining_pdf_structured_import","remaining_pdf_explicit_answer_marker","remaining_pdf_page_traced"],"practiceMode":"practice","practiceEligible":true,"reviewOnly":false},{"id":"q-remaining-49491ac44513e3700b","source":"北森题库","library":"北森题库","category":"数学运算","subCategory":"北森题库/24北森/其他/通用行测","setName":"通用行测各类题型汇总及参考答案","originalFile":"通用行测各类题型汇总及参考答案.pdf","originalPath":"北森题库/24北森/其他/通用行测各类题型汇总及参考答案.pdf","sourceRefs":[{"archive":"北森题库.zip","path":"北森题库/24北森/其他/通用行测各类题型汇总及参考答案.pdf","originalFile":"通用行测各类题型汇总及参考答案.pdf","questionNumber":"","pdfPage":741}],"questionType":"single","question":"48，65，80，103，120，149，168，（ ）。","options":[{"key":"A","text":"202"},{"key":"B","text":"203"},{"key":"C","text":"221"},{"key":"D","text":"233"}],"answer":["B"],"analysis":"对原数列作差后，得出新的数列为 17，15，23，17，29，19，这个新的数列属于交叉数列， 奇数项是一个等差数列， 公差为6， 偶数项是一个公差为2 的等差数列， 所以接下来的数为35， 故空缺项为168+35=203， 因此，本题答案为 B 选项","images":[],"imageRefs":[],"ocrText":"","tags":["数学运算","通用行测"],"importConfidence":0.93,"importNotes":["remaining_pdf_structured_import","remaining_pdf_explicit_answer_marker","remaining_pdf_page_traced"],"practiceMode":"practice","practiceEligible":true,"reviewOnly":false},{"id":"q-remaining-b123538b394fc0722c","source":"北森题库","library":"北森题库","category":"数学运算","subCategory":"北森题库/24北森/其他/通用行测","setName":"通用行测各类题型汇总及参考答案","originalFile":"通用行测各类题型汇总及参考答案.pdf","originalPath":"北森题库/24北森/其他/通用行测各类题型汇总及参考答案.pdf","sourceRefs":[{"archive":"北森题库.zip","path":"北森题库/24北森/其他/通用行测各类题型汇总及参考答案.pdf","originalFile":"通用行测各类题型汇总及参考答案.pdf","questionNumber":"","pdfPage":741}],"questionType":"single","question":"5，10，（ ），34，65，130。","options":[{"key":"A","text":"15"},{"key":"B","text":"16"},{"key":"C","text":"17"},{"key":"D","text":"18"}],"answer":["C"],"analysis":"两两分组： （5，10），（（ 17 ），34），（65，130）各组后项为前项的 2 倍。因此，本题答案 为 C 选项","images":[],"imageRefs":[],"ocrText":"","tags":["数学运算","通用行测"],"importConfidence":0.93,"importNotes":["remaining_pdf_structured_import","remaining_pdf_explicit_answer_marker","remaining_pdf_page_traced"],"practiceMode":"practice","practiceEligible":true,"reviewOnly":false},{"id":"q-remaining-bd276480f54c0f288c","source":"北森题库","library":"北森题库","category":"数学运算","subCategory":"北森题库/24北森/其他/通用行测","setName":"通用行测各类题型汇总及参考答案","originalFile":"通用行测各类题型汇总及参考答案.pdf","originalPath":"北森题库/24北森/其他/通用行测各类题型汇总及参考答案.pdf","sourceRefs":[{"archive":"北森题库.zip","path":"北森题库/24北森/其他/通用行测各类题型汇总及参考答案.pdf","originalFile":"通用行测各类题型汇总及参考答案.pdf","questionNumber":"","pdfPage":741}],"questionType":"single","question":"5，11，-3，7，-5，（ ）","options":[{"key":"A","text":"6"},{"key":"B","text":"7"},{"key":"C","text":"8"},{"key":"D","text":"9"}],"answer":["A"],"analysis":"第一种规律： （第2 项-第 1 项）/2=第 3 项，答案为[7-(-5)]/2=6 第二种规律：相邻两项之和 是等比数 列。16，8，4, 2 , ( )","images":[],"imageRefs":[],"ocrText":"","tags":["数学运算","通用行测"],"importConfidence":0.93,"importNotes":["remaining_pdf_structured_import","remaining_pdf_explicit_answer_marker","remaining_pdf_page_traced"],"practiceMode":"practice","practiceEligible":true,"reviewOnly":false},{"id":"q-remaining-9c9b454b47329a3774","source":"北森题库","library":"北森题库","category":"数学运算","subCategory":"北森题库/24北森/其他/通用行测","setName":"通用行测各类题型汇总及参考答案","originalFile":"通用行测各类题型汇总及参考答案.pdf","originalPath":"北森题库/24北森/其他/通用行测各类题型汇总及参考答案.pdf","sourceRefs":[{"archive":"北森题库.zip","path":"北森题库/24北森/其他/通用行测各类题型汇总及参考答案.pdf","originalFile":"通用行测各类题型汇总及参考答案.pdf","questionNumber":"","pdfPage":741}],"questionType":"single","question":"5， 13，15，27，29，45，（ ）。","options":[{"key":"A","text":"56"},{"key":"B","text":"47"},{"key":"C","text":"55"},{"key":"D","text":"64"}],"answer":["B"],"analysis":"相邻两项做差，两两做差得到 8，2，12，2，16，这个二级数列的奇数项 8，12，16 为等差 数列，偶数项为常数列 2，2。所以所求项为 45+2=47。因此，本题答案为 B 项。","images":[],"imageRefs":[],"ocrText":"","tags":["数学运算","通用行测"],"importConfidence":0.93,"importNotes":["remaining_pdf_structured_import","remaining_pdf_explicit_answer_marker","remaining_pdf_page_traced"],"practiceMode":"practice","practiceEligible":true,"reviewOnly":false},{"id":"q-remaining-2580f9b97a1d07702c","source":"北森题库","library":"北森题库","category":"数学运算","subCategory":"北森题库/24北森/其他/通用行测","setName":"通用行测各类题型汇总及参考答案","originalFile":"通用行测各类题型汇总及参考答案.pdf","originalPath":"北森题库/24北森/其他/通用行测各类题型汇总及参考答案.pdf","sourceRefs":[{"archive":"北森题库.zip","path":"北森题库/24北森/其他/通用行测各类题型汇总及参考答案.pdf","originalFile":"通用行测各类题型汇总及参考答案.pdf","questionNumber":"","pdfPage":741}],"questionType":"single","question":"5，16，50，153，（ ）。","options":[{"key":"A","text":"256"},{"key":"B","text":"369"},{"key":"C","text":"454"},{"key":"D","text":"463"}],"answer":["D"],"analysis":"通过观察数列， 可以发现，5×3+1=16，16×3+2=50，50×3+3=153， 即符合：An×3+n=An+1， 所以选项=153×3+4=463。因此，本题答案选择 D 选项。 【尾数法】","images":[],"imageRefs":[],"ocrText":"","tags":["数学运算","通用行测"],"importConfidence":0.93,"importNotes":["remaining_pdf_structured_import","remaining_pdf_explicit_answer_marker","remaining_pdf_page_traced"],"practiceMode":"practice","practiceEligible":true,"reviewOnly":false},{"id":"q-remaining-6ac77ad2e76ae68e3e","source":"北森题库","library":"北森题库","category":"数学运算","subCategory":"北森题库/24北森/其他/通用行测","setName":"通用行测各类题型汇总及参考答案","originalFile":"通用行测各类题型汇总及参考答案.pdf","originalPath":"北森题库/24北森/其他/通用行测各类题型汇总及参考答案.pdf","sourceRefs":[{"archive":"北森题库.zip","path":"北森题库/24北森/其他/通用行测各类题型汇总及参考答案.pdf","originalFile":"通用行测各类题型汇总及参考答案.pdf","questionNumber":"","pdfPage":741}],"questionType":"single","question":"-5，20，95，220（ ）","options":[{"key":"A","text":"395"},{"key":"B","text":"367"},{"key":"C","text":"252"},{"key":"D","text":"251"}],"answer":["A"],"analysis":"解法一： 题干中数据都是5 的倍数， 答案选择A。 解法二： 本题考查幂次数列，-5＝02－5,20 ＝52－5，95＝102－5，220＝152－5.因此答案为 202－5＝395","images":[],"imageRefs":[],"ocrText":"","tags":["数学运算","通用行测"],"importConfidence":0.93,"importNotes":["remaining_pdf_structured_import","remaining_pdf_explicit_answer_marker","remaining_pdf_page_traced"],"practiceMode":"practice","practiceEligible":true,"reviewOnly":false},{"id":"q-remaining-b656786c717cfbc6ae","source":"北森题库","library":"北森题库","category":"数学运算","subCategory":"北森题库/24北森/其他/通用行测","setName":"通用行测各类题型汇总及参考答案","originalFile":"通用行测各类题型汇总及参考答案.pdf","originalPath":"北森题库/24北森/其他/通用行测各类题型汇总及参考答案.pdf","sourceRefs":[{"archive":"北森题库.zip","path":"北森题库/24北森/其他/通用行测各类题型汇总及参考答案.pdf","originalFile":"通用行测各类题型汇总及参考答案.pdf","questionNumber":"","pdfPage":742}],"questionType":"single","question":"5，24，6，20，4，（ ），40，3。","options":[{"key":"A","text":"28"},{"key":"B","text":"30"},{"key":"C","text":"36"},{"key":"D","text":"42"}],"answer":["B"],"analysis":"两两分组，相邻两项的乘积都是 120，所以 4×30=120，因此，本题答案为 B 选项。","images":[],"imageRefs":[],"ocrText":"","tags":["数学运算","通用行测"],"importConfidence":0.93,"importNotes":["remaining_pdf_structured_import","remaining_pdf_explicit_answer_marker","remaining_pdf_page_traced"],"practiceMode":"practice","practiceEligible":true,"reviewOnly":false},{"id":"q-remaining-f78b97161e752b8b60","source":"北森题库","library":"北森题库","category":"数学运算","subCategory":"北森题库/24北森/其他/通用行测","setName":"通用行测各类题型汇总及参考答案","originalFile":"通用行测各类题型汇总及参考答案.pdf","originalPath":"北森题库/24北森/其他/通用行测各类题型汇总及参考答案.pdf","sourceRefs":[{"archive":"北森题库.zip","path":"北森题库/24北森/其他/通用行测各类题型汇总及参考答案.pdf","originalFile":"通用行测各类题型汇总及参考答案.pdf","questionNumber":"","pdfPage":742}],"questionType":"single","question":"5，3，4，1，9，（ ）。","options":[{"key":"A","text":"24"},{"key":"B","text":"11"},{"key":"C","text":"37"},{"key":"D","text":"64"}],"answer":["D"],"analysis":"（5－3）2=4，（3－4）2=1，（4－1）2=9，所以（ ）=（1－9）2=64。所以本题正确答案为 D。","images":[],"imageRefs":[],"ocrText":"","tags":["数学运算","通用行测"],"importConfidence":0.93,"importNotes":["remaining_pdf_structured_import","remaining_pdf_explicit_answer_marker","remaining_pdf_page_traced"],"practiceMode":"practice","practiceEligible":true,"reviewOnly":false},{"id":"q-remaining-79ccd3eab20bc77e0d","source":"北森题库","library":"北森题库","category":"数学运算","subCategory":"北森题库/24北森/其他/通用行测","setName":"通用行测各类题型汇总及参考答案","originalFile":"通用行测各类题型汇总及参考答案.pdf","originalPath":"北森题库/24北森/其他/通用行测各类题型汇总及参考答案.pdf","sourceRefs":[{"archive":"北森题库.zip","path":"北森题库/24北森/其他/通用行测各类题型汇总及参考答案.pdf","originalFile":"通用行测各类题型汇总及参考答案.pdf","questionNumber":"","pdfPage":742}],"questionType":"single","question":"5，3 ， 7/3，2，9/5，5/3，（ ）","options":[{"key":"A","text":"13/8"},{"key":"B","text":"11/7"},{"key":"C","text":"7/5"},{"key":"D","text":"1"}],"answer":["B"],"analysis":"本题属于分数数列， 不能找到分子分母之间的联系， 则用反约分寻找分子分母各自的独立性， 原数列可化为：分子分母都是等差数列，因此，本题答案为 B 选项。","images":[],"imageRefs":[],"ocrText":"","tags":["数学运算","通用行测"],"importConfidence":0.93,"importNotes":["remaining_pdf_structured_import","remaining_pdf_explicit_answer_marker","remaining_pdf_page_traced"],"practiceMode":"practice","practiceEligible":true,"reviewOnly":false},{"id":"q-remaining-d5fae0a37dd69f0f40","source":"北森题库","library":"北森题库","category":"数学运算","subCategory":"北森题库/24北森/其他/通用行测","setName":"通用行测各类题型汇总及参考答案","originalFile":"通用行测各类题型汇总及参考答案.pdf","originalPath":"北森题库/24北森/其他/通用行测各类题型汇总及参考答案.pdf","sourceRefs":[{"archive":"北森题库.zip","path":"北森题库/24北森/其他/通用行测各类题型汇总及参考答案.pdf","originalFile":"通用行测各类题型汇总及参考答案.pdf","questionNumber":"","pdfPage":742}],"questionType":"single","question":"5，5，15，75（ ）","options":[{"key":"A","text":"125"},{"key":"B","text":"350"},{"key":"C","text":"455"},{"key":"D","text":"525"}],"answer":["D"],"analysis":"本题考查做商数列，特征非常明显，两两做商得到 1,3,5,（） ，所以答案为75×7＝525.答案 选择 D。","images":[],"imageRefs":[],"ocrText":"","tags":["数学运算","通用行测"],"importConfidence":0.93,"importNotes":["remaining_pdf_structured_import","remaining_pdf_explicit_answer_marker","remaining_pdf_page_traced"],"practiceMode":"practice","practiceEligible":true,"reviewOnly":false},{"id":"q-remaining-6c8999ca31a4e00c3c","source":"北森题库","library":"北森题库","category":"数学运算","subCategory":"北森题库/24北森/其他/通用行测","setName":"通用行测各类题型汇总及参考答案","originalFile":"通用行测各类题型汇总及参考答案.pdf","originalPath":"北森题库/24北森/其他/通用行测各类题型汇总及参考答案.pdf","sourceRefs":[{"archive":"北森题库.zip","path":"北森题库/24北森/其他/通用行测各类题型汇总及参考答案.pdf","originalFile":"通用行测各类题型汇总及参考答案.pdf","questionNumber":"","pdfPage":742}],"questionType":"single","question":"5，6，16，28，60，（ ）","options":[{"key":"A","text":"74"},{"key":"B","text":"82"},{"key":"C","text":"92"},{"key":"D","text":"116"}],"answer":["D"],"analysis":"本题属于递推数列。递推规律为：5×2-4=6，6×2+4=16，16×2-4=28，28×2+4=60，所以","images":[],"imageRefs":[],"ocrText":"","tags":["数学运算","通用行测"],"importConfidence":0.93,"importNotes":["remaining_pdf_structured_import","remaining_pdf_explicit_answer_marker","remaining_pdf_page_traced"],"practiceMode":"practice","practiceEligible":true,"reviewOnly":false},{"id":"q-remaining-0ce0c5907a7350508f","source":"北森题库","library":"北森题库","category":"数学运算","subCategory":"北森题库/24北森/其他/通用行测","setName":"通用行测各类题型汇总及参考答案","originalFile":"通用行测各类题型汇总及参考答案.pdf","originalPath":"北森题库/24北森/其他/通用行测各类题型汇总及参考答案.pdf","sourceRefs":[{"archive":"北森题库.zip","path":"北森题库/24北森/其他/通用行测各类题型汇总及参考答案.pdf","originalFile":"通用行测各类题型汇总及参考答案.pdf","questionNumber":"","pdfPage":743}],"questionType":"single","question":"5，6，9，18，45，（ ）","options":[{"key":"A","text":"96"},{"key":"B","text":"106"},{"key":"C","text":"116"},{"key":"D","text":"126"}],"answer":["D"],"analysis":"解法一：原数列做一次差，得1，3，9，27，为等比数列，所以下一项为 81+45=126。因此， 本题答案选择 D 选项。解法二：后一项等于前一项的三倍减去 9，所以下一项为 45×3-9=126。因此，本题答案选择 D 选项。 解法三： 后一项等于前一项减去3 后的三倍， 所以下一项为 （45-3）×3=126。 因此， 本题答案选择D 选项。","images":[],"imageRefs":[],"ocrText":"","tags":["数学运算","通用行测"],"importConfidence":0.93,"importNotes":["remaining_pdf_structured_import","remaining_pdf_explicit_answer_marker","remaining_pdf_page_traced"],"practiceMode":"practice","practiceEligible":true,"reviewOnly":false},{"id":"q-remaining-4c748e543e76505b22","source":"北森题库","library":"北森题库","category":"数学运算","subCategory":"北森题库/24北森/其他/通用行测","setName":"通用行测各类题型汇总及参考答案","originalFile":"通用行测各类题型汇总及参考答案.pdf","originalPath":"北森题库/24北森/其他/通用行测各类题型汇总及参考答案.pdf","sourceRefs":[{"archive":"北森题库.zip","path":"北森题库/24北森/其他/通用行测各类题型汇总及参考答案.pdf","originalFile":"通用行测各类题型汇总及参考答案.pdf","questionNumber":"","pdfPage":743}],"questionType":"single","question":"5，7，10，15，22，（ ）","options":[{"key":"A","text":"28"},{"key":"B","text":"30"},{"key":"C","text":"33"},{"key":"D","text":"35"}],"answer":["C"],"analysis":"两两作差 2，3，5，7，质数数列，所以后一项为 11，答案为 22+11=33","images":[],"imageRefs":[],"ocrText":"","tags":["数学运算","通用行测"],"importConfidence":0.93,"importNotes":["remaining_pdf_structured_import","remaining_pdf_explicit_answer_marker","remaining_pdf_page_traced"],"practiceMode":"practice","practiceEligible":true,"reviewOnly":false},{"id":"q-remaining-86300ef61a1c1df8cc","source":"北森题库","library":"北森题库","category":"数学运算","subCategory":"北森题库/24北森/其他/通用行测","setName":"通用行测各类题型汇总及参考答案","originalFile":"通用行测各类题型汇总及参考答案.pdf","originalPath":"北森题库/24北森/其他/通用行测各类题型汇总及参考答案.pdf","sourceRefs":[{"archive":"北森题库.zip","path":"北森题库/24北森/其他/通用行测各类题型汇总及参考答案.pdf","originalFile":"通用行测各类题型汇总及参考答案.pdf","questionNumber":"","pdfPage":743}],"questionType":"single","question":"5,7,11,15,23,（ ）。","options":[{"key":"A","text":"25"},{"key":"B","text":"27"},{"key":"C","text":"28"},{"key":"D","text":"29"}],"answer":["B"],"analysis":"B 5=2X2+1，7=2X3+1，11=2X5+1，15=2X7+1，23=2X11+1，2,3,5,7,11,（13）为质数数列，所 以括号里为 2X13+1=（27） ，因此，本题答案为B 选项。","images":[],"imageRefs":[],"ocrText":"","tags":["数学运算","通用行测"],"importConfidence":0.93,"importNotes":["remaining_pdf_structured_import","remaining_pdf_explicit_answer_marker","remaining_pdf_page_traced"],"practiceMode":"practice","practiceEligible":true,"reviewOnly":false},{"id":"q-remaining-a38bf535fa040caf9f","source":"北森题库","library":"北森题库","category":"数学运算","subCategory":"北森题库/24北森/其他/通用行测","setName":"通用行测各类题型汇总及参考答案","originalFile":"通用行测各类题型汇总及参考答案.pdf","originalPath":"北森题库/24北森/其他/通用行测各类题型汇总及参考答案.pdf","sourceRefs":[{"archive":"北森题库.zip","path":"北森题库/24北森/其他/通用行测各类题型汇总及参考答案.pdf","originalFile":"通用行测各类题型汇总及参考答案.pdf","questionNumber":"","pdfPage":743}],"questionType":"single","question":"5，7， 25，9， 125，11，（ ）。","options":[{"key":"A","text":"13"},{"key":"B","text":"17"},{"key":"C","text":"625"},{"key":"D","text":"225"}],"answer":["C"],"analysis":"原数列的奇数项是一个公比为 5 的等比数列：5，25，125，（625） ；偶数项是一个公差为2 的等差数列：7，9，11。因此，本题答案为 C 选项。","images":[],"imageRefs":[],"ocrText":"","tags":["数学运算","通用行测"],"importConfidence":0.93,"importNotes":["remaining_pdf_structured_import","remaining_pdf_explicit_answer_marker","remaining_pdf_page_traced"],"practiceMode":"practice","practiceEligible":true,"reviewOnly":false},{"id":"q-remaining-0a3299cbf36bf48c12","source":"北森题库","library":"北森题库","category":"数学运算","subCategory":"北森题库/24北森/其他/通用行测","setName":"通用行测各类题型汇总及参考答案","originalFile":"通用行测各类题型汇总及参考答案.pdf","originalPath":"北森题库/24北森/其他/通用行测各类题型汇总及参考答案.pdf","sourceRefs":[{"archive":"北森题库.zip","path":"北森题库/24北森/其他/通用行测各类题型汇总及参考答案.pdf","originalFile":"通用行测各类题型汇总及参考答案.pdf","questionNumber":"","pdfPage":743}],"questionType":"single","question":"5，8，13，21，34，（ ）。","options":[{"key":"A","text":"45"},{"key":"B","text":"50"},{"key":"C","text":"55"},{"key":"D","text":"60"}],"answer":["C"],"analysis":"数列第三项起每项为前两项之和，因此答案为 21+34=55。因此，本题答案为 C 选项。","images":[],"imageRefs":[],"ocrText":"","tags":["数学运算","通用行测"],"importConfidence":0.93,"importNotes":["remaining_pdf_structured_import","remaining_pdf_explicit_answer_marker","remaining_pdf_page_traced"],"practiceMode":"practice","practiceEligible":true,"reviewOnly":false},{"id":"q-remaining-2d924d29d6f92a5189","source":"北森题库","library":"北森题库","category":"数学运算","subCategory":"北森题库/24北森/其他/通用行测","setName":"通用行测各类题型汇总及参考答案","originalFile":"通用行测各类题型汇总及参考答案.pdf","originalPath":"北森题库/24北森/其他/通用行测各类题型汇总及参考答案.pdf","sourceRefs":[{"archive":"北森题库.zip","path":"北森题库/24北森/其他/通用行测各类题型汇总及参考答案.pdf","originalFile":"通用行测各类题型汇总及参考答案.pdf","questionNumber":"","pdfPage":743}],"questionType":"single","question":"5，9，11，17，（ ）","options":[{"key":"A","text":"21"},{"key":"B","text":"22"},{"key":"C","text":"26"},{"key":"D","text":"30"}],"answer":["A"],"analysis":"数列中项数较少，且变化趋势不明显，考虑多级数列，相邻两项之间找规律，做差没有明 显规律，所以考虑两项之间加和，5+9=14，9+11=20，11+17=28，做和之后形成二级数列 14、20、28、（38）， 对 二 级数列做差分别是 6、8、（ 10） ，那么二级数列下一项为28+10=38，所以一级数列下一项为 38—17=21 ，因此本题 答案为 21，所以选择 A 选项。","images":[],"imageRefs":[],"ocrText":"","tags":["数学运算","通用行测"],"importConfidence":0.93,"importNotes":["remaining_pdf_structured_import","remaining_pdf_explicit_answer_marker","remaining_pdf_page_traced"],"practiceMode":"practice","practiceEligible":true,"reviewOnly":false},{"id":"q-remaining-c7d053b3183c63f534","source":"北森题库","library":"北森题库","category":"数学运算","subCategory":"北森题库/24北森/其他/通用行测","setName":"通用行测各类题型汇总及参考答案","originalFile":"通用行测各类题型汇总及参考答案.pdf","originalPath":"北森题库/24北森/其他/通用行测各类题型汇总及参考答案.pdf","sourceRefs":[{"archive":"北森题库.zip","path":"北森题库/24北森/其他/通用行测各类题型汇总及参考答案.pdf","originalFile":"通用行测各类题型汇总及参考答案.pdf","questionNumber":"","pdfPage":744}],"questionType":"single","question":"5/6 6/11 11/17 （ ） 28/45","options":[{"key":"A","text":"17/24"},{"key":"B","text":"17/28"},{"key":"C","text":"28/17"},{"key":"D","text":"24/17"}],"answer":["B"],"analysis":"本题考察分数数列，后项分子为前项的分母，后项分母为前项的分子、分母之和，所以（） 的分子应为 17，分母为 17+11=28，因此答案选择 B 选项。","images":[],"imageRefs":[],"ocrText":"","tags":["数学运算","通用行测"],"importConfidence":0.93,"importNotes":["remaining_pdf_structured_import","remaining_pdf_explicit_answer_marker","remaining_pdf_page_traced"],"practiceMode":"practice","practiceEligible":true,"reviewOnly":false},{"id":"q-remaining-449668c0be3101417e","source":"北森题库","library":"北森题库","category":"数学运算","subCategory":"北森题库/24北森/其他/通用行测","setName":"通用行测各类题型汇总及参考答案","originalFile":"通用行测各类题型汇总及参考答案.pdf","originalPath":"北森题库/24北森/其他/通用行测各类题型汇总及参考答案.pdf","sourceRefs":[{"archive":"北森题库.zip","path":"北森题库/24北森/其他/通用行测各类题型汇总及参考答案.pdf","originalFile":"通用行测各类题型汇总及参考答案.pdf","questionNumber":"","pdfPage":744}],"questionType":"single","question":"512，422，413，332，233，（ ）","options":[{"key":"A","text":"151"},{"key":"B","text":"126"},{"key":"C","text":"108"},{"key":"D","text":"206"}],"answer":["D"],"analysis":"数列各项数字之和均为 8。5+1+2=8，4+2+2=8，4+1+3=8，3+3+2=8，2+3+3=8。选项中只有 D 符合。因此，答案选择 D 选项。","images":[],"imageRefs":[],"ocrText":"","tags":["数学运算","通用行测"],"importConfidence":0.93,"importNotes":["remaining_pdf_structured_import","remaining_pdf_explicit_answer_marker","remaining_pdf_page_traced"],"practiceMode":"practice","practiceEligible":true,"reviewOnly":false},{"id":"q-remaining-68aad8005981e3774b","source":"北森题库","library":"北森题库","category":"数学运算","subCategory":"北森题库/24北森/其他/通用行测","setName":"通用行测各类题型汇总及参考答案","originalFile":"通用行测各类题型汇总及参考答案.pdf","originalPath":"北森题库/24北森/其他/通用行测各类题型汇总及参考答案.pdf","sourceRefs":[{"archive":"北森题库.zip","path":"北森题库/24北森/其他/通用行测各类题型汇总及参考答案.pdf","originalFile":"通用行测各类题型汇总及参考答案.pdf","questionNumber":"","pdfPage":744}],"questionType":"single","question":"52，-56，-92，-104，（ ）","options":[{"key":"A","text":"-100"},{"key":"B","text":"-107"},{"key":"C","text":"-108"},{"key":"D","text":"-112"}],"answer":["C"],"analysis":"原数列前后两两做差， 可得：108、36、12、（4） ， 构成等比数列， 可得未知项为 -104-4＝-108。 因此，本题选 C。","images":[],"imageRefs":[],"ocrText":"","tags":["数学运算","通用行测"],"importConfidence":0.93,"importNotes":["remaining_pdf_structured_import","remaining_pdf_explicit_answer_marker","remaining_pdf_page_traced"],"practiceMode":"practice","practiceEligible":true,"reviewOnly":false},{"id":"q-remaining-eca33fc4dda8f23b12","source":"北森题库","library":"北森题库","category":"数学运算","subCategory":"北森题库/24北森/其他/通用行测","setName":"通用行测各类题型汇总及参考答案","originalFile":"通用行测各类题型汇总及参考答案.pdf","originalPath":"北森题库/24北森/其他/通用行测各类题型汇总及参考答案.pdf","sourceRefs":[{"archive":"北森题库.zip","path":"北森题库/24北森/其他/通用行测各类题型汇总及参考答案.pdf","originalFile":"通用行测各类题型汇总及参考答案.pdf","questionNumber":"53","pdfPage":744}],"questionType":"single","question":"，48，50，45，47，（ ）。","options":[{"key":"A","text":"38"},{"key":"B","text":"42"},{"key":"C","text":"46"},{"key":"D","text":"51"}],"answer":["B"],"analysis":"原数列相邻两项做差，可得周期数列：因此，本题答案为 B 选项。","images":[],"imageRefs":[],"ocrText":"","tags":["数学运算","通用行测"],"importConfidence":0.93,"importNotes":["remaining_pdf_structured_import","remaining_pdf_explicit_answer_marker","remaining_pdf_page_traced"],"practiceMode":"practice","practiceEligible":true,"reviewOnly":false},{"id":"q-remaining-0aa4026ab849aca018","source":"北森题库","library":"北森题库","category":"数学运算","subCategory":"北森题库/24北森/其他/通用行测","setName":"通用行测各类题型汇总及参考答案","originalFile":"通用行测各类题型汇总及参考答案.pdf","originalPath":"北森题库/24北森/其他/通用行测各类题型汇总及参考答案.pdf","sourceRefs":[{"archive":"北森题库.zip","path":"北森题库/24北森/其他/通用行测各类题型汇总及参考答案.pdf","originalFile":"通用行测各类题型汇总及参考答案.pdf","questionNumber":"","pdfPage":744}],"questionType":"single","question":"58，71，84，97，（ ）。","options":[{"key":"A","text":"100"},{"key":"B","text":"106"},{"key":"C","text":"109"},{"key":"D","text":"110"}],"answer":["D"],"analysis":"原数列为公差为 13 的等差数列，所以下一项为 97+13=110。因此，本题答案为 D 选项。","images":[],"imageRefs":[],"ocrText":"","tags":["数学运算","通用行测"],"importConfidence":0.93,"importNotes":["remaining_pdf_structured_import","remaining_pdf_explicit_answer_marker","remaining_pdf_page_traced"],"practiceMode":"practice","practiceEligible":true,"reviewOnly":false},{"id":"q-remaining-0a439b3e8d21fb320e","source":"北森题库","library":"北森题库","category":"数学运算","subCategory":"北森题库/24北森/其他/通用行测","setName":"通用行测各类题型汇总及参考答案","originalFile":"通用行测各类题型汇总及参考答案.pdf","originalPath":"北森题库/24北森/其他/通用行测各类题型汇总及参考答案.pdf","sourceRefs":[{"archive":"北森题库.zip","path":"北森题库/24北森/其他/通用行测各类题型汇总及参考答案.pdf","originalFile":"通用行测各类题型汇总及参考答案.pdf","questionNumber":"","pdfPage":745}],"questionType":"single","question":"6 4 8 9 12 9（ ）26 30","options":[{"key":"A","text":"12"},{"key":"B","text":"16"},{"key":"C","text":"18"},{"key":"D","text":"22"}],"answer":["B"],"analysis":"将原数列首尾两项相加，可以得到：6+30=36，4+26=30，8+（16）=（24），9+9=18，12； 而 36，30，（24），18，12 构成一个公差为-6 的等差数列。因此，本题答案为 B 选项。","images":[],"imageRefs":[],"ocrText":"","tags":["数学运算","通用行测"],"importConfidence":0.93,"importNotes":["remaining_pdf_structured_import","remaining_pdf_explicit_answer_marker","remaining_pdf_page_traced"],"practiceMode":"practice","practiceEligible":true,"reviewOnly":false},{"id":"q-remaining-766feb0d012b68fe9e","source":"北森题库","library":"北森题库","category":"数学运算","subCategory":"北森题库/24北森/其他/通用行测","setName":"通用行测各类题型汇总及参考答案","originalFile":"通用行测各类题型汇总及参考答案.pdf","originalPath":"北森题库/24北森/其他/通用行测各类题型汇总及参考答案.pdf","sourceRefs":[{"archive":"北森题库.zip","path":"北森题库/24北森/其他/通用行测各类题型汇总及参考答案.pdf","originalFile":"通用行测各类题型汇总及参考答案.pdf","questionNumber":"","pdfPage":745}],"questionType":"single","question":"6, 11, 17, （ ）, 45","options":[{"key":"A","text":"30"},{"key":"B","text":"28"},{"key":"C","text":"25"},{"key":"D","text":"22"}],"answer":["B"],"analysis":"递推和数列，前两项和等于第三项。17=6+11，（ ）=11+17, 45=（ ）+17，选择 B。","images":[],"imageRefs":[],"ocrText":"","tags":["数学运算","通用行测"],"importConfidence":0.93,"importNotes":["remaining_pdf_structured_import","remaining_pdf_explicit_answer_marker","remaining_pdf_page_traced"],"practiceMode":"practice","practiceEligible":true,"reviewOnly":false},{"id":"q-remaining-fd839980a19374f84c","source":"北森题库","library":"北森题库","category":"数学运算","subCategory":"北森题库/24北森/其他/通用行测","setName":"通用行测各类题型汇总及参考答案","originalFile":"通用行测各类题型汇总及参考答案.pdf","originalPath":"北森题库/24北森/其他/通用行测各类题型汇总及参考答案.pdf","sourceRefs":[{"archive":"北森题库.zip","path":"北森题库/24北森/其他/通用行测各类题型汇总及参考答案.pdf","originalFile":"通用行测各类题型汇总及参考答案.pdf","questionNumber":"","pdfPage":745}],"questionType":"single","question":"6，14，22，（ ），38，46","options":[{"key":"A","text":"30"},{"key":"B","text":"32"},{"key":"C","text":"34"},{"key":"D","text":"36"}],"answer":["A"],"analysis":"很容易能够看出相邻数字之间的差值是8， 是一个公差为8 的等差数列，30 刚好吻合， 因此， 本题答案为 A 选项。","images":[],"imageRefs":[],"ocrText":"","tags":["数学运算","通用行测"],"importConfidence":0.93,"importNotes":["remaining_pdf_structured_import","remaining_pdf_explicit_answer_marker","remaining_pdf_page_traced"],"practiceMode":"practice","practiceEligible":true,"reviewOnly":false},{"id":"q-remaining-013513eafb60038872","source":"北森题库","library":"北森题库","category":"数学运算","subCategory":"北森题库/24北森/其他/通用行测","setName":"通用行测各类题型汇总及参考答案","originalFile":"通用行测各类题型汇总及参考答案.pdf","originalPath":"北森题库/24北森/其他/通用行测各类题型汇总及参考答案.pdf","sourceRefs":[{"archive":"北森题库.zip","path":"北森题库/24北森/其他/通用行测各类题型汇总及参考答案.pdf","originalFile":"通用行测各类题型汇总及参考答案.pdf","questionNumber":"","pdfPage":745}],"questionType":"single","question":"6，16，56，132，250，( )","options":[{"key":"A","text":"498"},{"key":"B","text":"512"},{"key":"C","text":"416"},{"key":"D","text":"52"}],"answer":["C"],"analysis":"三级等差数列。 相邻两项做差得到：10、40、76、118 ， 再次做差得到：30、36 、42、（ 48）， 以 6 为公差的等差数列，未知项=250+48+118，尾数为 6。因此，本题答案为 C 选项。","images":[],"imageRefs":[],"ocrText":"","tags":["数学运算","通用行测"],"importConfidence":0.93,"importNotes":["remaining_pdf_structured_import","remaining_pdf_explicit_answer_marker","remaining_pdf_page_traced"],"practiceMode":"practice","practiceEligible":true,"reviewOnly":false},{"id":"q-remaining-17b04f30a197282493","source":"北森题库","library":"北森题库","category":"数学运算","subCategory":"北森题库/24北森/其他/通用行测","setName":"通用行测各类题型汇总及参考答案","originalFile":"通用行测各类题型汇总及参考答案.pdf","originalPath":"北森题库/24北森/其他/通用行测各类题型汇总及参考答案.pdf","sourceRefs":[{"archive":"北森题库.zip","path":"北森题库/24北森/其他/通用行测各类题型汇总及参考答案.pdf","originalFile":"通用行测各类题型汇总及参考答案.pdf","questionNumber":"","pdfPage":745}],"questionType":"single","question":"6，20，42，72，110，（ ）","options":[{"key":"A","text":"128"},{"key":"B","text":"140"},{"key":"C","text":"156"},{"key":"D","text":"166"}],"answer":["C"],"analysis":"相邻两项做差，两两做差得到 14，22，30，38，这是一个等差数列，下一项应该是 46，所 求项为 110+46=156。因此，本题答案为 C 项。","images":[],"imageRefs":[],"ocrText":"","tags":["数学运算","通用行测"],"importConfidence":0.93,"importNotes":["remaining_pdf_structured_import","remaining_pdf_explicit_answer_marker","remaining_pdf_page_traced"],"practiceMode":"practice","practiceEligible":true,"reviewOnly":false},{"id":"q-remaining-7606ef3044559e3db9","source":"北森题库","library":"北森题库","category":"数学运算","subCategory":"北森题库/24北森/其他/通用行测","setName":"通用行测各类题型汇总及参考答案","originalFile":"通用行测各类题型汇总及参考答案.pdf","originalPath":"北森题库/24北森/其他/通用行测各类题型汇总及参考答案.pdf","sourceRefs":[{"archive":"北森题库.zip","path":"北森题库/24北森/其他/通用行测各类题型汇总及参考答案.pdf","originalFile":"通用行测各类题型汇总及参考答案.pdf","questionNumber":"","pdfPage":745}],"questionType":"single","question":"6，3，5，13，2，63，（ ）","options":[{"key":"A","text":"-36"},{"key":"B","text":"-37"},{"key":"C","text":"-38"},{"key":"D","text":"-39"}],"answer":["B"],"analysis":"本题规律为 An+3=An×An+1-An+2：13=6×3-5、2=3×5-13、63=5×13-2、（ ）=13×2-63=-37。 因此，本题答案选择 B 选项。","images":[],"imageRefs":[],"ocrText":"","tags":["数学运算","通用行测"],"importConfidence":0.93,"importNotes":["remaining_pdf_structured_import","remaining_pdf_explicit_answer_marker","remaining_pdf_page_traced"],"practiceMode":"practice","practiceEligible":true,"reviewOnly":false},{"id":"q-remaining-6c7c84cd5e022414ff","source":"北森题库","library":"北森题库","category":"数学运算","subCategory":"北森题库/24北森/其他/通用行测","setName":"通用行测各类题型汇总及参考答案","originalFile":"通用行测各类题型汇总及参考答案.pdf","originalPath":"北森题库/24北森/其他/通用行测各类题型汇总及参考答案.pdf","sourceRefs":[{"archive":"北森题库.zip","path":"北森题库/24北森/其他/通用行测各类题型汇总及参考答案.pdf","originalFile":"通用行测各类题型汇总及参考答案.pdf","questionNumber":"","pdfPage":746}],"questionType":"single","question":"6，7，18，23，（ ），47。","options":[{"key":"A","text":"25"},{"key":"B","text":"38"},{"key":"C","text":"40"},{"key":"D","text":"45"}],"answer":["B"],"analysis":"6=22+2，7=32-2，18=42+2，23=52-2，所以， （ ）=62+2=38。因此，本题答案为 B 选项。","images":[],"imageRefs":[],"ocrText":"","tags":["数学运算","通用行测"],"importConfidence":0.93,"importNotes":["remaining_pdf_structured_import","remaining_pdf_explicit_answer_marker","remaining_pdf_page_traced"],"practiceMode":"practice","practiceEligible":true,"reviewOnly":false},{"id":"q-remaining-9620bc032af47d3a0f","source":"北森题库","library":"北森题库","category":"数学运算","subCategory":"北森题库/24北森/其他/通用行测","setName":"通用行测各类题型汇总及参考答案","originalFile":"通用行测各类题型汇总及参考答案.pdf","originalPath":"北森题库/24北森/其他/通用行测各类题型汇总及参考答案.pdf","sourceRefs":[{"archive":"北森题库.zip","path":"北森题库/24北森/其他/通用行测各类题型汇总及参考答案.pdf","originalFile":"通用行测各类题型汇总及参考答案.pdf","questionNumber":"","pdfPage":746}],"questionType":"single","question":"6,7,3,0,3,3,6,9, （ ）","options":[{"key":"A","text":"5"},{"key":"B","text":"6"},{"key":"C","text":"7"},{"key":"D","text":"8"}],"answer":["A"],"analysis":"从第三项开始，最后一项等于前面两项的和留尾数，括号处等于6+9=15 留尾数 5，因此，本 题答案为 A 选项。","images":[],"imageRefs":[],"ocrText":"","tags":["数学运算","通用行测"],"importConfidence":0.93,"importNotes":["remaining_pdf_structured_import","remaining_pdf_explicit_answer_marker","remaining_pdf_page_traced"],"practiceMode":"practice","practiceEligible":true,"reviewOnly":false},{"id":"q-remaining-0fd74d062f30358019","source":"北森题库","library":"北森题库","category":"数学运算","subCategory":"北森题库/24北森/其他/通用行测","setName":"通用行测各类题型汇总及参考答案","originalFile":"通用行测各类题型汇总及参考答案.pdf","originalPath":"北森题库/24北森/其他/通用行测各类题型汇总及参考答案.pdf","sourceRefs":[{"archive":"北森题库.zip","path":"北森题库/24北森/其他/通用行测各类题型汇总及参考答案.pdf","originalFile":"通用行测各类题型汇总及参考答案.pdf","questionNumber":"","pdfPage":746}],"questionType":"single","question":"6，7，5，8，4，9，（ ）","options":[{"key":"A","text":"5"},{"key":"B","text":"10"},{"key":"C","text":"3"},{"key":"D","text":"4"}],"answer":["C"],"analysis":"解法一： 数列的变化趋势为震荡形式， 因此可以优先考虑为交叉数列， 奇数项6，5，4，（3）； 偶数项 7，8，9，故答案为 3。因此，本题答案为 C 选 项。解法二：两两做和，得到的数列为 13、12、13、12 、13， 这是一个周期数列，故空缺项为 12－9＝3。","images":[],"imageRefs":[],"ocrText":"","tags":["数学运算","通用行测"],"importConfidence":0.93,"importNotes":["remaining_pdf_structured_import","remaining_pdf_explicit_answer_marker","remaining_pdf_page_traced"],"practiceMode":"practice","practiceEligible":true,"reviewOnly":false},{"id":"q-remaining-03c8bc11125669d5f1","source":"北森题库","library":"北森题库","category":"数学运算","subCategory":"北森题库/24北森/其他/通用行测","setName":"通用行测各类题型汇总及参考答案","originalFile":"通用行测各类题型汇总及参考答案.pdf","originalPath":"北森题库/24北森/其他/通用行测各类题型汇总及参考答案.pdf","sourceRefs":[{"archive":"北森题库.zip","path":"北森题库/24北森/其他/通用行测各类题型汇总及参考答案.pdf","originalFile":"通用行测各类题型汇总及参考答案.pdf","questionNumber":"","pdfPage":746}],"questionType":"single","question":"6/28,21/98,18/84,9/42，（ ）","options":[{"key":"A","text":"25/60"},{"key":"B","text":"12/44"},{"key":"C","text":"12/56"},{"key":"D","text":"25/78"}],"answer":["C"],"analysis":"原数列中的各项约分后均为 3/14， 则空缺项也应约分后为3/14。 因此， 本题答案为C 选项。","images":[],"imageRefs":[],"ocrText":"","tags":["数学运算","通用行测"],"importConfidence":0.93,"importNotes":["remaining_pdf_structured_import","remaining_pdf_explicit_answer_marker","remaining_pdf_page_traced"],"practiceMode":"practice","practiceEligible":true,"reviewOnly":false},{"id":"q-remaining-465ee7f981b9a1ec7d","source":"北森题库","library":"北森题库","category":"数学运算","subCategory":"北森题库/24北森/其他/通用行测","setName":"通用行测各类题型汇总及参考答案","originalFile":"通用行测各类题型汇总及参考答案.pdf","originalPath":"北森题库/24北森/其他/通用行测各类题型汇总及参考答案.pdf","sourceRefs":[{"archive":"北森题库.zip","path":"北森题库/24北森/其他/通用行测各类题型汇总及参考答案.pdf","originalFile":"通用行测各类题型汇总及参考答案.pdf","questionNumber":"","pdfPage":746}],"questionType":"single","question":"60，90，108，120，（ ）。","options":[{"key":"A","text":"147"},{"key":"B","text":"138.42"},{"key":"C","text":"128.57"},{"key":"D","text":"125.36"}],"answer":["C"],"analysis":"C 通过观察可以发现，60 为正三角形内角度数，90 为正方形内角度数，108 为正五边形内 角度数，120 为正六边形内角度数，所以括号中应为正七边形内角度数。正多边形内角度数公式为（n-2 ）180°/n。 因此，本题答案为 128.57，C 选项。","images":[],"imageRefs":[],"ocrText":"","tags":["数学运算","通用行测"],"importConfidence":0.93,"importNotes":["remaining_pdf_structured_import","remaining_pdf_explicit_answer_marker","remaining_pdf_page_traced"],"practiceMode":"practice","practiceEligible":true,"reviewOnly":false},{"id":"q-remaining-d54faa5693a4361b57","source":"北森题库","library":"北森题库","category":"数学运算","subCategory":"北森题库/24北森/其他/通用行测","setName":"通用行测各类题型汇总及参考答案","originalFile":"通用行测各类题型汇总及参考答案.pdf","originalPath":"北森题库/24北森/其他/通用行测各类题型汇总及参考答案.pdf","sourceRefs":[{"archive":"北森题库.zip","path":"北森题库/24北森/其他/通用行测各类题型汇总及参考答案.pdf","originalFile":"通用行测各类题型汇总及参考答案.pdf","questionNumber":"","pdfPage":747}],"questionType":"single","question":"637951，59736，6795，976，（ ）。","options":[{"key":"A","text":"96"},{"key":"B","text":"69"},{"key":"C","text":"76"},{"key":"D","text":"67"}],"answer":["B"],"analysis":"解法一：观察发现，这些数里有很多相同的部分，仔细观察发现，数列里后面的一个数是通 过前面一个数推出来的，第一个数值，舍去最后一位数字，然后再从倒数第二位开始逆着写就可以得出第二个数； 第二个数值，舍去倒数第二位，然后再逆着写就可以得出第三个数；第三个数值，舍去倒数第一位，然后再逆着写 就可以得出第四个数值；按规律，第四个数值，舍去倒数第二位，然后就逆着写就可以得出答案 69，因此，本题答 案选 B 选项。解法二：观察数列，每一项数都位数较多，且变化紊乱，因此优先考虑机械分组。在该数列中，下一 项比前一项少一位数，且少的数字是 1、3、5；而剩余的数字再反向顺序排列，照此规律，下一项少的数字是 7，且 剩余的 96 变化为 69。因此，本题答案选 B 选项。","images":[],"imageRefs":[],"ocrText":"","tags":["数学运算","通用行测"],"importConfidence":0.93,"importNotes":["remaining_pdf_structured_import","remaining_pdf_explicit_answer_marker","remaining_pdf_page_traced"],"practiceMode":"practice","practiceEligible":true,"reviewOnly":false},{"id":"q-remaining-bc8b16bcf641953c0b","source":"北森题库","library":"北森题库","category":"数学运算","subCategory":"北森题库/24北森/其他/通用行测","setName":"通用行测各类题型汇总及参考答案","originalFile":"通用行测各类题型汇总及参考答案.pdf","originalPath":"北森题库/24北森/其他/通用行测各类题型汇总及参考答案.pdf","sourceRefs":[{"archive":"北森题库.zip","path":"北森题库/24北森/其他/通用行测各类题型汇总及参考答案.pdf","originalFile":"通用行测各类题型汇总及参考答案.pdf","questionNumber":"","pdfPage":747}],"questionType":"single","question":"67，49，55，37，43，25，（ ）","options":[{"key":"A","text":"28"},{"key":"B","text":"31"},{"key":"C","text":"36"},{"key":"D","text":"40"}],"answer":["B"],"analysis":"奇数项：67,55,43， （） 为公差-12 的等差数列， 所以选项=43+（-12）=31， 偶数项：49，37,25， 也为公差为-12 的等差数列，因此，本题答案选择 B 选项。","images":[],"imageRefs":[],"ocrText":"","tags":["数学运算","通用行测"],"importConfidence":0.93,"importNotes":["remaining_pdf_structured_import","remaining_pdf_explicit_answer_marker","remaining_pdf_page_traced"],"practiceMode":"practice","practiceEligible":true,"reviewOnly":false},{"id":"q-remaining-ea99a107adaa4e10e6","source":"北森题库","library":"北森题库","category":"数学运算","subCategory":"北森题库/24北森/其他/通用行测","setName":"通用行测各类题型汇总及参考答案","originalFile":"通用行测各类题型汇总及参考答案.pdf","originalPath":"北森题库/24北森/其他/通用行测各类题型汇总及参考答案.pdf","sourceRefs":[{"archive":"北森题库.zip","path":"北森题库/24北森/其他/通用行测各类题型汇总及参考答案.pdf","originalFile":"通用行测各类题型汇总及参考答案.pdf","questionNumber":"","pdfPage":747}],"questionType":"single","question":"675，225，90，45，30，30，（ ）。","options":[{"key":"A","text":"27"},{"key":"B","text":"38"},{"key":"C","text":"60"},{"key":"D","text":"124"}],"answer":["C"],"analysis":"前项和后项作商后，为一个等差数列。675÷225=3，225÷90=2.5，90÷45=2，45÷30=1.5， 30÷30=1,故下一项为 30÷0.5=60。故应选 C。","images":[],"imageRefs":[],"ocrText":"","tags":["数学运算","通用行测"],"importConfidence":0.93,"importNotes":["remaining_pdf_structured_import","remaining_pdf_explicit_answer_marker","remaining_pdf_page_traced"],"practiceMode":"practice","practiceEligible":true,"reviewOnly":false}]